Workbook
Name Slicer_Month: #N/A
Name Slicer_Year: #N/A

Sheet Dashboard

Sheet Pivots
A3: Row Labels | B3: Sum of Total_Sales
A4: January | B4: 1072821
A5: February | B5: 901743
A6: March | B6: 1001401
A7: April | B7: 991871
A8: May | B8: 1028459
A9: June | B9: 1016595
A10: July | B10: 1017551
A11: August | B11: 1011035
A12: September | B12: 991556
A13: October | B13: 1010560
A14: November | B14: 1006190
A15: December | B15: 986315
A16: Grand Total | B16: 12036097
A22: Row Labels | B22: Average of RevPar
A23: January | B23: 1235.9689
A24: February | B24: 1130.0038
A25: March | B25: 1153.6878
A26: April | B26: 1180.7988
A27: May | B27: 1184.8606
A28: June | B28: 1210.2321
A29: July | B29: 1172.2938
A30: August | B30: 1164.7869
A31: September | B31: 1180.4238
A32: October | B32: 1164.2396
A33: November | B33: 1197.8452
A34: December | B34: 1136.3076
A39: Row Labels | B39: Average of ADR
A40: January | B40: 1574.8226
A41: February | B41: 1460.1754
A42: March | B42: 1476.6613
A43: April | B43: 1520.8833
A44: May | B44: 1488.0968
A45: June | B45: 1524.7667
A46: July | B46: 1529.4032
A47: August | B47: 1507.6774
A48: September | B48: 1507.4333
A49: October | B49: 1523.9839
A50: November | B50: 1476.7
A51: December | B51: 1486.1774
A57: Row Labels | B57: Sum of Total_Daily_Expense
A58: January | B58: 943012.62
A59: February | B59: 898882.46
A60: March | B60: 922140.22
A61: April | B61: 979421.62
A62: May | B62: 992550.98
A63: June | B63: 980563.9
A64: July | B64: 987206.22
A65: August | B65: 984417.7
A66: September | B66: 981629.32
A67: October | B67: 984060.2
A68: November | B68: 983774.8
A69: December | B69: 977615.3
A70: Grand Total | B70: 11615275
A76: Row Labels | B76: Average of ADR | C76: Average of Occupancy %
A77: January | B77: 1574.8226 | C77: 0.77995392
A78: February | B78: 1460.1754 | C78: 0.77318296
A79: March | B79: 1476.6613 | C79: 0.77995392
A80: April | B80: 1520.8833 | C80: 0.77619048
A81: May | B81: 1488.0968 | C81: 0.79493088
A82: June | B82: 1524.7667 | C82: 0.78809524
A83: July | B83: 1529.4032 | C83: 0.76497696
A84: August | B84: 1507.6774 | C84: 0.7718894
A85: September | B85: 1507.4333 | C85: 0.78809524
A86: October | B86: 1523.9839 | C86: 0.76152074
A87: November | B87: 1476.7 | C87: 0.80595238
A88: December | B88: 1486.1774 | C88: 0.76612903
A97: Row Labels | B97: Sum of Rooms_Occupied
A98: January | B98: 677
A99: February | B99: 617
A100: March | B100: 677
A101: April | B101: 652
A102: May | B102: 690
A103: June | B103: 662
A104: July | B104: 664
A105: August | B105: 670
A106: September | B106: 662
A107: October | B107: 661
A108: November | B108: 677
A109: December | B109: 665
A110: Grand Total | B110: 7974
A114: Year | B114: (All)
A116: Row Labels | B116: Sum of Profit
A117: January | B117: 129808.38
A118: February | B118: 2860.54
A119: March | B119: 79260.78
A120: April | B120: 12449.38
A121: May | B121: 35908.02
A122: June | B122: 36031.1
A123: July | B123: 30344.78
A124: August | B124: 26617.3
A125: September | B125: 9926.68
A126: October | B126: 26499.8
A127: November | B127: 22415.2
A128: December | B128: 8699.7
A129: Grand Total | B129: 420821.66
A142: Row Labels | B142: Sum of Daily_Rent | C142: Sum of Daily_Staff | D142: Sum of Daily_HK | E142: Sum of Daily_Electricity | F142: Sum of Daily Maintenance
A143: January | B143: 400000 | C143: 140000 | D143: 20000 | E143: 106992 | F143: 40000
A144: February | B144: 400000 | C144: 140000 | D144: 20000 | E144: 100499 | F144: 40000
A145: March | B145: 400000 | C145: 140000 | D145: 20000 | E145: 101832 | F145: 40000
...

Sheet Daily_data
A1: Date | B1: Month_key | C1: Month | D1: Year | E1: Rooms_Occupied | F1: Max_rooms | G1: Occupancy_rate | H1: Room_rate | I1: Total_Sales | J1: OTA Commision | K1: Daily_Rent | L1: Daily_Staff | M1: Daily_HK | N1: Daily_Electricity | O1: Daily Maintenance | P1: Total_Daily_Expense | Q1: Profit | R1: ADR | S1: RevPar
A2: 44927 | B2: =DATE(YEAR(Daily_Data[[#This Row],[Date]]), MONTH(Daily_Data[[#This Row],[Date]]), 1) -> 44927 | C2: =TEXT(Daily_Data[[#This Row],[Month_key]],"mmmm") -> January | D2: =TEXT(Daily_Data[[#This Row],[Month_key]],"yyyy") -> 2023 | E2: 12 | F2: 14 | G2: =Daily_Data[[#This Row],[Rooms_Occupied]]/F2 -> 0.85714286 | H2: 1687 | I2: =Daily_Data[[#This Row],[Room_rate]]*Daily_Data[[#This Row],[Rooms_Occupied]] -> 20244 | J2: =Daily_Data[[#This Row],[Total_Sales]] * 0.22 -> 4453.68 | K2: =INDEX(Expense_master[Monthly_Rent],MATCH(Daily_Data[[#This Row],[Month_key]],Expense_master[Month_Key],0)) / INDEX(Expense_master[Days_in_Month],MATCH(Daily_Data[[#This Row],[Month_key]],Expense_master[Month_Key],0)) -> 6129.0323 | L2: =SUMIFS(Expense_master[Staff_Salary],Expense_master[Month_Key],Daily_Data[[#This Row],[Month_key]]) / SUMIFS(Expense_master[Days_in_Month],Expense_master[Month_Key],Daily_Data[[#This Row],[Month_key]]) -> 2258.0645 | M2: =Daily_Data[[#This Row],[Rooms_Occupied]] * (SUMIFS(Expense_master[Housekeeping_Laundy],Expense_master[Month_Key],Daily_Data[[#This Row],[Month_key]]) / SUMIFS(Occupancy_table[Monthly_rooms_Occupied],Occupancy_table[Month_Key],Daily_Data[[#This Row],[Month_key]])) -> 335.19553 | N2: =0.4 * (SUMIFS(Expense_master[Electicity_Bill],Expense_master[Month_Key],Daily_Data[[#This Row],[Month_key]]) / SUMIFS(Expense_master[Days_in_Month],Expense_master[Month_Key],Daily_Data[[#This Row],[Month_key]])) + Daily_Data[[#This Row],[Rooms_Occupied]] * ( (0.6 * SUMIFS(Expense_master[Electicity_Bill],Expense_master[Month_Key], Daily_Data[[#This Row],[Month_key]])) / SUMIFS(Occupancy_table[Monthly_rooms_Occupied],Occupancy_table[Month_Key],Daily_Data[[#This Row],[Month_key]])) -> 1740.2844 | O2: =SUMIFS(Expense_master[Monthly_Maintenance],Expense_master[Month_Key],Daily_Data[[#This Row],[Month_key]]) / SUMIFS(Expense_master[Days_in_Month],Expense_master[Month_Key], Daily_Data[[#This Row],[Month_key]]) -> 645.16129 | P2: =Daily_Data[[#This Row],[OTA Commision]] + Daily_Data[[#This Row],[Daily_Rent]]+Daily_Data[[#This Row],[Daily_Staff]]+Daily_Data[[#This Row],[Daily_HK]]+Daily_Data[[#This Row],[Daily_Electricity]] + Daily_Data[[#This Row],[Daily Maintenance]] -> 15561.418 | Q2: =Daily_Data[[#This Row],[Total_Sales]]-Daily_Data[[#This Row],[Total_Daily_Expense]] -> 4682.582 | R2: =Daily_Data[[#This Row],[Total_Sales]]/Daily_Data[[#This Row],[Rooms_Occupied]] -> 1687 | S2: =Daily_Data[[#This Row],[Total_Sales]] / Daily_Data[[#This Row],[Max_rooms]] -> 1446
A3: 44928 | B3: =DATE(YEAR(Daily_Data[[#This Row],[Date]]), MONTH(Daily_Data[[#This Row],[Date]]), 1) -> 44927 | C3: =TEXT(Daily_Data[[#This Row],[Month_key]],"mmmm") -> January | D3: =TEXT(Daily_Data[[#This Row],[Month_key]],"yyyy") -> 2023 | E3: 12 | F3: 14 | G3: =Daily_Data[[#This Row],[Rooms_Occupied]]/F3 -> 0.85714286 | H3: 1458 | I3: =Daily_Data[[#This Row],[Room_rate]]*Daily_Data[[#This Row],[Rooms_Occupied]] -> 17496 | J3: =Daily_Data[[#This Row],[Total_Sales]] * 0.22 -> 3849.12 | K3: =INDEX(Expense_master[Monthly_Rent],MATCH(Daily_Data[[#This Row],[Month_key]],Expense_master[Month_Key],0)) / INDEX(Expense_master[Days_in_Month],MATCH(Daily_Data[[#This Row],[Month_key]],Expense_master[Month_Key],0)) -> 6129.0323 | L3: =SUMIFS(Expense_master[Staff_Salary],Expense_master[Month_Key],Daily_Data[[#This Row],[Month_key]]) / SUMIFS(Expense_master[Days_in_Month],Expense_master[Month_Key],Daily_Data[[#This Row],[Month_key]]) -> 2258.0645 | M3: =Daily_Data[[#This Row],[Rooms_Occupied]] * (SUMIFS(Expense_master[Housekeeping_Laundy],Expense_master[Month_Key],Daily_Data[[#This Row],[Month_key]]) / SUMIFS(Occupancy_table[Monthly_rooms_Occupied],Occupancy_table[Month_Key],Daily_Data[[#This Row],[Month_key]])) -> 335.19553 | N3: =0.4 * (SUMIFS(Expense_master[Electicity_Bill],Expense_master[Month_Key],Daily_Data[[#This Row],[Month_key]]) / SUMIFS(Expense_master[Days_in_Month],Expense_master[Month_Key],Daily_Data[[#This Row],[Month_key]])) + Daily_Data[[#This Row],[Rooms_Occupied]] * ( (0.6 * SUMIFS(Expense_master[Electicity_Bill],Expense_master[Month_Key], Daily_Data[[#This Row],[Month_key]])) / SUMIFS(Occupancy_table[Monthly_rooms_Occupied],Occupancy_table[Month_Key],Daily_Data[[#This Row],[Month_key]])) -> 1740.2844 | O3: =SUMIFS(Expense_master[Monthly_Maintenance],Expense_master[Month_Key],Daily_Data[[#This Row],[Month_key]]) / SUMIFS(Expense_master[Days_in_Month],Expense_master[Month_Key], Daily_Data[[#This Row],[Month_key]]) -> 645.16129 | P3: =Daily_Data[[#This Row],[OTA Commision]] + Daily_Data[[#This Row],[Daily_Rent]]+Daily_Data[[#This Row],[Daily_Staff]]+Daily_Data[[#This Row],[Daily_HK]]+Daily_Data[[#This Row],[Daily_Electricity]] + Daily_Data[[#This Row],[Daily Maintenance]] -> 14956.858 | Q3: =Daily_Data[[#This Row],[Total_Sales]]-Daily_Data[[#This Row],[Total_Daily_Expense]] -> 2539.142 | R3: =Daily_Data[[#This Row],[Total_Sales]]/Daily_Data[[#This Row],[Rooms_Occupied]] -> 1458 | S3: =Daily_Data[[#This Row],[Total_Sales]] / Daily_Data[[#This Row],[Max_rooms]] -> 1249.7143
A4: 44929 | B4: =DATE(YEAR(Daily_Data[[#This Row],[Date]]), MONTH(Daily_Data[[#This Row],[Date]]), 1) -> 44927 | C4: =TEXT(Daily_Data[[#This Row],[Month_key]],"mmmm") -> January | D4: =TEXT(Daily_Data[[#This Row],[Month_key]],"yyyy") -> 2023 | E4: 12 | F4: 14 | G4: =Daily_Data[[#This Row],[Rooms_Occupied]]/F4 -> 0.85714286 | H4: 1561 | I4: =Daily_Data[[#This Row],[Room_rate]]*Daily_Data[[#This Row],[Rooms_Occupied]] -> 18732 | J4: =Daily_Data[[#This Row],[Total_Sales]] * 0.22 -> 4121.04 | K4: =INDEX(Expense_master[Monthly_Rent],MATCH(Daily_Data[[#This Row],[Month_key]],Expense_master[Month_Key],0)) / INDEX(Expense_master[Days_in_Month],MATCH(Daily_Data[[#This Row],[Month_key]],Expense_master[Month_Key],0)) -> 6129.0323 | L4: =SUMIFS(Expense_master[Staff_Salary],Expense_master[Month_Key],Daily_Data[[#This Row],[Month_key]]) / SUMIFS(Expense_master[Days_in_Month],Expense_master[Month_Key],Daily_Data[[#This Row],[Month_key]]) -> 2258.0645 | M4: =Daily_Data[[#This Row],[Rooms_Occupied]] * (SUMIFS(Expense_master[Housekeeping_Laundy],Expense_master[Month_Key],Daily_Data[[#This Row],[Month_key]]) / SUMIFS(Occupancy_table[Monthly_rooms_Occupied],Occupancy_table[Month_Key],Daily_Data[[#This Row],[Month_key]])) -> 335.19553 | N4: =0.4 * (SUMIFS(Expense_master[Electicity_Bill],Expense_master[Month_Key],Daily_Data[[#This Row],[Month_key]]) / SUMIFS(Expense_master[Days_in_Month],Expense_master[Month_Key],Daily_Data[[#This Row],[Month_key]])) + Daily_Data[[#This Row],[Rooms_Occupied]] * ( (0.6 * SUMIFS(Expense_master[Electicity_Bill],Expense_master[Month_Key], Daily_Data[[#This Row],[Month_key]])) / SUMIFS(Occupancy_table[Monthly_rooms_Occupied],Occupancy_table[Month_Key],Daily_Data[[#This Row],[Month_key]])) -> 1740.2844 | O4: =SUMIFS(Expense_master[Monthly_Maintenance],Expense_master[Month_Key],Daily_Data[[#This Row],[Month_key]]) / SUMIFS(Expense_master[Days_in_Month],Expense_master[Month_Key], Daily_Data[[#This Row],[Month_key]]) -> 645.16129 | P4: =Daily_Data[[#This Row],[OTA Commision]] + Daily_Data[[#This Row],[Daily_Rent]]+Daily_Data[[#This Row],[Daily_Staff]]+Daily_Data[[#This Row],[Daily_HK]]+Daily_Data[[#This Row],[Daily_Electricity]] + Daily_Data[[#This Row],[Daily Maintenance]] -> 15228.778 | Q4: =Daily_Data[[#This Row],[Total_Sales]]-Daily_Data[[#This Row],[Total_Daily_Expense]] -> 3503.222 | R4: =Daily_Data[[#This Row],[Total_Sales]]/Daily_Data[[#This Row],[Rooms_Occupied]] -> 1561 | S4: =Daily_Data[[#This Row],[Total_Sales]] / Daily_Data[[#This Row],[Max_rooms]] -> 1338
A5: 44930 | B5: =DATE(YEAR(Daily_Data[[#This Row],[Date]]), MONTH(Daily_Data[[#This Row],[Date]]), 1) -> 44927 | C5: =TEXT(Daily_Data[[#This Row],[Month_key]],"mmmm") -> January | D5: =TEXT(Daily_Data[[#This Row],[Month_key]],"yyyy") -> 2023 | E5: 11 | F5: 14 | G5: =Daily_Data[[#This Row],[Rooms_Occupied]]/F5 -> 0.78571429 | H5: 1970 | I5: =Daily_Data[[#This Row],[Room_rate]]*Daily_Data[[#This Row],[Rooms_Occupied]] -> 21670 | J5: =Daily_Data[[#This Row],[Total_Sales]] * 0.22 -> 4767.4 | K5: =INDEX(Expense_master[Monthly_Rent],MATCH(Daily_Data[[#This Row],[Month_key]],Expense_master[Month_Key],0)) / INDEX(Expense_master[Days_in_Month],MATCH(Daily_Data[[#This Row],[Month_key]],Expense_master[Month_Key],0)) -> 6129.0323 | L5: =SUMIFS(Expense_master[Staff_Salary],Expense_master[Month_Key],Daily_Data[[#This Row],[Month_key]]) / SUMIFS(Expense_master[Days_in_Month],Expense_master[Month_Key],Daily_Data[[#This Row],[Month_key]]) -> 2258.0645 | M5: =Daily_Data[[#This Row],[Rooms_Occupied]] * (SUMIFS(Expense_master[Housekeeping_Laundy],Expense_master[Month_Key],Daily_Data[[#This Row],[Month_key]]) / SUMIFS(Occupancy_table[Monthly_rooms_Occupied],Occupancy_table[Month_Key],Daily_Data[[#This Row],[Month_key]])) -> 307.26257 | N5: =0.4 * (SUMIFS(Expense_master[Electicity_Bill],Expense_master[Month_Key],Daily_Data[[#This Row],[Month_key]]) / SUMIFS(Expense_master[Days_in_Month],Expense_master[Month_Key],Daily_Data[[#This Row],[Month_key]])) + Daily_Data[[#This Row],[Rooms_Occupied]] * ( (0.6 * SUMIFS(Expense_master[Electicity_Bill],Expense_master[Month_Key], Daily_Data[[#This Row],[Month_key]])) / SUMIFS(Occupancy_table[Monthly_rooms_Occupied],Occupancy_table[Month_Key],Daily_Data[[#This Row],[Month_key]])) -> 1651.9403 | O5: =SUMIFS(Expense_master[Monthly_Maintenance],Expense_master[Month_Key],Daily_Data[[#This Row],[Month_key]]) / SUMIFS(Expense_master[Days_in_Month],Expense_master[Month_Key], Daily_Data[[#This Row],[Month_key]]) -> 645.16129 | P5: =Daily_Data[[#This Row],[OTA Commision]] + Daily_Data[[#This Row],[Daily_Rent]]+Daily_Data[[#This Row],[Daily_Staff]]+Daily_Data[[#This Row],[Daily_HK]]+Daily_Data[[#This Row],[Daily_Electricity]] + Daily_Data[[#This Row],[Daily Maintenance]] -> 15758.861 | Q5: =Daily_Data[[#This Row],[Total_Sales]]-Daily_Data[[#This Row],[Total_Daily_Expense]] -> 5911.1391 | R5: =Daily_Data[[#This Row],[Total_Sales]]/Daily_Data[[#This Row],[Rooms_Occupied]] -> 1970 | S5: =Daily_Data[[#This Row],[Total_Sales]] / Daily_Data[[#This Row],[Max_rooms]] -> 1547.8571
A6: 44931 | B6: =DATE(YEAR(Daily_Data[[#This Row],[Date]]), MONTH(Daily_Data[[#This Row],[Date]]), 1) -> 44927 | C6: =TEXT(Daily_Data[[#This Row],[Month_key]],"mmmm") -> January | D6: =TEXT(Daily_Data[[#This Row],[Month_key]],"yyyy") -> 2023 | E6: 12 | F6: 14 | G6: =Daily_Data[[#This Row],[Rooms_Occupied]]/F6 -> 0.85714286 | H6: 1556 | I6: =Daily_Data[[#This Row],[Room_rate]]*Daily_Data[[#This Row],[Rooms_Occupied]] -> 18672 | J6: =Daily_Data[[#This Row],[Total_Sales]] * 0.22 -> 4107.84 | K6: =INDEX(Expense_master[Monthly_Rent],MATCH(Daily_Data[[#This Row],[Month_key]],Expense_master[Month_Key],0)) / INDEX(Expense_master[Days_in_Month],MATCH(Daily_Data[[#This Row],[Month_key]],Expense_master[Month_Key],0)) -> 6129.0323 | L6: =SUMIFS(Expense_master[Staff_Salary],Expense_master[Month_Key],Daily_Data[[#This Row],[Month_key]]) / SUMIFS(Expense_master[Days_in_Month],Expense_master[Month_Key],Daily_Data[[#This Row],[Month_key]]) -> 2258.0645 | M6: =Daily_Data[[#This Row],[Rooms_Occupied]] * (SUMIFS(Expense_master[Housekeeping_Laundy],Expense_master[Month_Key],Daily_Data[[#This Row],[Month_key]]) / SUMIFS(Occupancy_table[Monthly_rooms_Occupied],Occupancy_table[Month_Key],Daily_Data[[#This Row],[Month_key]])) -> 335.19553 | N6: =0.4 * (SUMIFS(Expense_master[Electicity_Bill],Expense_master[Month_Key],Daily_Data[[#This Row],[Month_key]]) / SUMIFS(Expense_master[Days_in_Month],Expense_master[Month_Key],Daily_Data[[#This Row],[Month_key]])) + Daily_Data[[#This Row],[Rooms_Occupied]] * ( (0.6 * SUMIFS(Expense_master[Electicity_Bill],Expense_master[Month_Key], Daily_Data[[#This Row],[Month_key]])) / SUMIFS(Occupancy_table[Monthly_rooms_Occupied],Occupancy_table[Month_Key],Daily_Data[[#This Row],[Month_key]])) -> 1740.2844 | O6: =SUMIFS(Expense_master[Monthly_Maintenance],Expense_master[Month_Key],Daily_Data[[#This Row],[Month_key]]) / SUMIFS(Expense_master[Days_in_Month],Expense_master[Month_Key], Daily_Data[[#This Row],[Month_key]]) -> 645.16129 | P6: =Daily_Data[[#This Row],[OTA Commision]] + Daily_Data[[#This Row],[Daily_Rent]]+Daily_Data[[#This Row],[Daily_Staff]]+Daily_Data[[#This Row],[Daily_HK]]+Daily_Data[[#This Row],[Daily_Electricity]] + Daily_Data[[#This Row],[Daily Maintenance]] -> 15215.578 | Q6: =Daily_Data[[#This Row],[Total_Sales]]-Daily_Data[[#This Row],[Total_Daily_Expense]] -> 3456.422 | R6: =Daily_Data[[#This Row],[Total_Sales]]/Daily_Data[[#This Row],[Rooms_Occupied]] -> 1556 | S6: =Daily_Data[[#This Row],[Total_Sales]] / Daily_Data[[#This Row],[Max_rooms]] -> 1333.7143
A7: 44932 | B7: =DATE(YEAR(Daily_Data[[#This Row],[Date]]), MONTH(Daily_Data[[#This Row],[Date]]), 1) -> 44927 | C7: =TEXT(Daily_Data[[#This Row],[Month_key]],"mmmm") -> January | D7: =TEXT(Daily_Data[[#This Row],[Month_key]],"yyyy") -> 2023 | E7: 13 | F7: 14 | G7: =Daily_Data[[#This Row],[Rooms_Occupied]]/F7 -> 0.92857143 | H7: 1572 | I7: =Daily_Data[[#This Row],[Room_rate]]*Daily_Data[[#This Row],[Rooms_Occupied]] -> 20436 | J7: =Daily_Data[[#This Row],[Total_Sales]] * 0.22 -> 4495.92 | K7: =INDEX(Expense_master[Monthly_Rent],MATCH(Daily_Data[[#This Row],[Month_key]],Expense_master[Month_Key],0)) / INDEX(Expense_master[Days_in_Month],MATCH(Daily_Data[[#This Row],[Month_key]],Expense_master[Month_Key],0)) -> 6129.0323 | L7: =SUMIFS(Expense_master[Staff_Salary],Expense_master[Month_Key],Daily_Data[[#This Row],[Month_key]]) / SUMIFS(Expense_master[Days_in_Month],Expense_master[Month_Key],Daily_Data[[#This Row],[Month_key]]) -> 2258.0645 | M7: =Daily_Data[[#This Row],[Rooms_Occupied]] * (SUMIFS(Expense_master[Housekeeping_Laundy],Expense_master[Month_Key],Daily_Data[[#This Row],[Month_key]]) / SUMIFS(Occupancy_table[Monthly_rooms_Occupied],Occupancy_table[Month_Key],Daily_Data[[#This Row],[Month_key]])) -> 363.12849 | N7: =0.4 * (SUMIFS(Expense_master[Electicity_Bill],Expense_master[Month_Key],Daily_Data[[#This Row],[Month_key]]) / SUMIFS(Expense_master[Days_in_Month],Expense_master[Month_Key],Daily_Data[[#This Row],[Month_key]])) + Daily_Data[[#This Row],[Rooms_Occupied]] * ( (0.6 * SUMIFS(Expense_master[Electicity_Bill],Expense_master[Month_Key], Daily_Data[[#This Row],[Month_key]])) / SUMIFS(Occupancy_table[Monthly_rooms_Occupied],Occupancy_table[Month_Key],Daily_Data[[#This Row],[Month_key]])) -> 1828.6286 | O7: =SUMIFS(Expense_master[Monthly_Maintenance],Expense_master[Month_Key],Daily_Data[[#This Row],[Month_key]]) / SUMIFS(Expense_master[Days_in_Month],Expense_master[Month_Key], Daily_Data[[#This Row],[Month_key]]) -> 645.16129 | P7: =Daily_Data[[#This Row],[OTA Commision]] + Daily_Data[[#This Row],[Daily_Rent]]+Daily_Data[[#This Row],[Daily_Staff]]+Daily_Data[[#This Row],[Daily_HK]]+Daily_Data[[#This Row],[Daily_Electricity]] + Daily_Data[[#This Row],[Daily Maintenance]] -> 15719.935 | Q7: =Daily_Data[[#This Row],[Total_Sales]]-Daily_Data[[#This Row],[Total_Daily_Expense]] -> 4716.0649 | R7: =Daily_Data[[#This Row],[Total_Sales]]/Daily_Data[[#This Row],[Rooms_Occupied]] -> 1572 | S7: =Daily_Data[[#This Row],[Total_Sales]] / Daily_Data[[#This Row],[Max_rooms]] -> 1459.7143
A8: 44933 | B8: =DATE(YEAR(Daily_Data[[#This Row],[Date]]), MONTH(Daily_Data[[#This Row],[Date]]), 1) -> 44927 | C8: =TEXT(Daily_Data[[#This Row],[Month_key]],"mmmm") -> January | D8: =TEXT(Daily_Data[[#This Row],[Month_key]],"yyyy") -> 2023 | E8: 14 | F8: 14 | G8: =Daily_Data[[#This Row],[Rooms_Occupied]]/F8 -> 1 | H8: 1922 | I8: =Daily_Data[[#This Row],[Room_rate]]*Daily_Data[[#This Row],[Rooms_Occupied]] -> 26908 | J8: =Daily_Data[[#This Row],[Total_Sales]] * 0.22 -> 5919.76 | K8: =INDEX(Expense_master[Monthly_Rent],MATCH(Daily_Data[[#This Row],[Month_key]],Expense_master[Month_Key],0)) / INDEX(Expense_master[Days_in_Month],MATCH(Daily_Data[[#This Row],[Month_key]],Expense_master[Month_Key],0)) -> 6129.0323 | L8: =SUMIFS(Expense_master[Staff_Salary],Expense_master[Month_Key],Daily_Data[[#This Row],[Month_key]]) / SUMIFS(Expense_master[Days_in_Month],Expense_master[Month_Key],Daily_Data[[#This Row],[Month_key]]) -> 2258.0645 | M8: =Daily_Data[[#This Row],[Rooms_Occupied]] * (SUMIFS(Expense_master[Housekeeping_Laundy],Expense_master[Month_Key],Daily_Data[[#This Row],[Month_key]]) / SUMIFS(Occupancy_table[Monthly_rooms_Occupied],Occupancy_table[Month_Key],Daily_Data[[#This Row],[Month_key]])) -> 391.06145 | N8: =0.4 * (SUMIFS(Expense_master[Electicity_Bill],Expense_master[Month_Key],Daily_Data[[#This Row],[Month_key]]) / SUMIFS(Expense_master[Days_in_Month],Expense_master[Month_Key],Daily_Data[[#This Row],[Month_key]])) + Daily_Data[[#This Row],[Rooms_Occupied]] * ( (0.6 * SUMIFS(Expense_master[Electicity_Bill],Expense_master[Month_Key], Daily_Data[[#This Row],[Month_key]])) / SUMIFS(Occupancy_table[Monthly_rooms_Occupied],Occupancy_table[Month_Key],Daily_Data[[#This Row],[Month_key]])) -> 1916.9727 | O8: =SUMIFS(Expense_master[Monthly_Maintenance],Expense_master[Month_Key],Daily_Data[[#This Row],[Month_key]]) / SUMIFS(Expense_master[Days_in_Month],Expense_master[Month_Key], Daily_Data[[#This Row],[Month_key]]) -> 645.16129 | P8: =Daily_Data[[#This Row],[OTA Commision]] + Daily_Data[[#This Row],[Daily_Rent]]+Daily_Data[[#This Row],[Daily_Staff]]+Daily_Data[[#This Row],[Daily_HK]]+Daily_Data[[#This Row],[Daily_Electricity]] + Daily_Data[[#This Row],[Daily Maintenance]] -> 17260.052 | Q8: =Daily_Data[[#This Row],[Total_Sales]]-Daily_Data[[#This Row],[Total_Daily_Expense]] -> 9647.9478 | R8: =Daily_Data[[#This Row],[Total_Sales]]/Daily_Data[[#This Row],[Rooms_Occupied]] -> 1922 | S8: =Daily_Data[[#This Row],[Total_Sales]] / Daily_Data[[#This Row],[Max_rooms]] -> 1922
A9: 44934 | B9: =DATE(YEAR(Daily_Data[[#This Row],[Date]]), MONTH(Daily_Data[[#This Row],[Date]]), 1) -> 44927 | C9: =TEXT(Daily_Data[[#This Row],[Month_key]],"mmmm") -> January | D9: =TEXT(Daily_Data[[#This Row],[Month_key]],"yyyy") -> 2023 | E9: 13 | F9: 14 | G9: =Daily_Data[[#This Row],[Rooms_Occupied]]/F9 -> 0.92857143 | H9: 1588 | I9: =Daily_Data[[#This Row],[Room_rate]]*Daily_Data[[#This Row],[Rooms_Occupied]] -> 20644 | J9: =Daily_Data[[#This Row],[Total_Sales]] * 0.22 -> 4541.68 | K9: =INDEX(Expense_master[Monthly_Rent],MATCH(Daily_Data[[#This Row],[Month_key]],Expense_master[Month_Key],0)) / INDEX(Expense_master[Days_in_Month],MATCH(Daily_Data[[#This Row],[Month_key]],Expense_master[Month_Key],0)) -> 6129.0323 | L9: =SUMIFS(Expense_master[Staff_Salary],Expense_master[Month_Key],Daily_Data[[#This Row],[Month_key]]) / SUMIFS(Expense_master[Days_in_Month],Expense_master[Month_Key],Daily_Data[[#This Row],[Month_key]]) -> 2258.0645 | M9: =Daily_Data[[#This Row],[Rooms_Occupied]] * (SUMIFS(Expense_master[Housekeeping_Laundy],Expense_master[Month_Key],Daily_Data[[#This Row],[Month_key]]) / SUMIFS(Occupancy_table[Monthly_rooms_Occupied],Occupancy_table[Month_Key],Daily_Data[[#This Row],[Month_key]])) -> 363.12849 | N9: =0.4 * (SUMIFS(Expense_master[Electicity_Bill],Expense_master[Month_Key],Daily_Data[[#This Row],[Month_key]]) / SUMIFS(Expense_master[Days_in_Month],Expense_master[Month_Key],Daily_Data[[#This Row],[Month_key]])) + Daily_Data[[#This Row],[Rooms_Occupied]] * ( (0.6 * SUMIFS(Expense_master[Electicity_Bill],Expense_master[Month_Key], Daily_Data[[#This Row],[Month_key]])) / SUMIFS(Occupancy_table[Monthly_rooms_Occupied],Occupancy_table[Month_Key],Daily_Data[[#This Row],[Month_key]])) -> 1828.6286 | O9: =SUMIFS(Expense_master[Monthly_Maintenance],Expense_master[Month_Key],Daily_Data[[#This Row],[Month_key]]) / SUMIFS(Expense_master[Days_in_Month],Expense_master[Month_Key], Daily_Data[[#This Row],[Month_key]]) -> 645.16129 | P9: =Daily_Data[[#This Row],[OTA Commision]] + Daily_Data[[#This Row],[Daily_Rent]]+Daily_Data[[#This Row],[Daily_Staff]]+Daily_Data[[#This Row],[Daily_HK]]+Daily_Data[[#This Row],[Daily_Electricity]] + Daily_Data[[#This Row],[Daily Maintenance]] -> 15765.695 | Q9: =Daily_Data[[#This Row],[Total_Sales]]-Daily_Data[[#This Row],[Total_Daily_Expense]] -> 4878.3049 | R9: =Daily_Data[[#This Row],[Total_Sales]]/Daily_Data[[#This Row],[Rooms_Occupied]] -> 1588 | S9: =Daily_Data[[#This Row],[Total_Sales]] / Daily_Data[[#This Row],[Max_rooms]] -> 1474.5714 | W9: Total Revenue | X9: =SUM(Daily_Data[Total_Sales]) -> 12036097
A10: 44935 | B10: =DATE(YEAR(Daily_Data[[#This Row],[Date]]), MONTH(Daily_Data[[#This Row],[Date]]), 1) -> 44927 | C10: =TEXT(Daily_Data[[#This Row],[Month_key]],"mmmm") -> January | D10: =TEXT(Daily_Data[[#This Row],[Month_key]],"yyyy") -> 2023 | E10: 12 | F10: 14 | G10: =Daily_Data[[#This Row],[Rooms_Occupied]]/F10 -> 0.85714286 | H10: 1540 | I10: =Daily_Data[[#This Row],[Room_rate]]*Daily_Data[[#This Row],[Rooms_Occupied]] -> 18480 | J10: =Daily_Data[[#This Row],[Total_Sales]] * 0.22 -> 4065.6 | K10: =INDEX(Expense_master[Monthly_Rent],MATCH(Daily_Data[[#This Row],[Month_key]],Expense_master[Month_Key],0)) / INDEX(Expense_master[Days_in_Month],MATCH(Daily_Data[[#This Row],[Month_key]],Expense_master[Month_Key],0)) -> 6129.0323 | L10: =SUMIFS(Expense_master[Staff_Salary],Expense_master[Month_Key],Daily_Data[[#This Row],[Month_key]]) / SUMIFS(Expense_master[Days_in_Month],Expense_master[Month_Key],Daily_Data[[#This Row],[Month_key]]) -> 2258.0645 | M10: =Daily_Data[[#This Row],[Rooms_Occupied]] * (SUMIFS(Expense_master[Housekeeping_Laundy],Expense_master[Month_Key],Daily_Data[[#This Row],[Month_key]]) / SUMIFS(Occupancy_table[Monthly_rooms_Occupied],Occupancy_table[Month_Key],Daily_Data[[#This Row],[Month_key]])) -> 335.19553 | N10: =0.4 * (SUMIFS(Expense_master[Electicity_Bill],Expense_master[Month_Key],Daily_Data[[#This Row],[Month_key]]) / SUMIFS(Expense_master[Days_in_Month],Expense_master[Month_Key],Daily_Data[[#This Row],[Month_key]])) + Daily_Data[[#This Row],[Rooms_Occupied]] * ( (0.6 * SUMIFS(Expense_master[Electicity_Bill],Expense_master[Month_Key], Daily_Data[[#This Row],[Month_key]])) / SUMIFS(Occupancy_table[Monthly_rooms_Occupied],Occupancy_table[Month_Key],Daily_Data[[#This Row],[Month_key]])) -> 1740.2844 | O10: =SUMIFS(Expense_master[Monthly_Maintenance],Expense_master[Month_Key],Daily_Data[[#This Row],[Month_key]]) / SUMIFS(Expense_master[Days_in_Month],Expense_master[Month_Key], Daily_Data[[#This Row],[Month_key]]) -> 645.16129 | P10: =Daily_Data[[#This Row],[OTA Commision]] + Daily_Data[[#This Row],[Daily_Rent]]+Daily_Data[[#This Row],[Daily_Staff]]+Daily_Data[[#This Row],[Daily_HK]]+Daily_Data[[#This Row],[Daily_Electricity]] + Daily_Data[[#This Row],[Daily Maintenance]] -> 15173.338 | Q10: =Daily_Data[[#This Row],[Total_Sales]]-Daily_Data[[#This Row],[Total_Daily_Expense]] -> 3306.662 | R10: =Daily_Data[[#This Row],[Total_Sales]]/Daily_Data[[#This Row],[Rooms_Occupied]] -> 1540 | S10: =Daily_Data[[#This Row],[Total_Sales]] / Daily_Data[[#This Row],[Max_rooms]] -> 1320 | W10: Avg ADR | X10: =AVERAGE(Daily_Data[ADR]) -> 1506.7031
A11: 44936 | B11: =DATE(YEAR(Daily_Data[[#This Row],[Date]]), MONTH(Daily_Data[[#This Row],[Date]]), 1) -> 44927 | C11: =TEXT(Daily_Data[[#This Row],[Month_key]],"mmmm") -> January | D11: =TEXT(Daily_Data[[#This Row],[Month_key]],"yyyy") -> 2023 | E11: 11 | F11: 14 | G11: =Daily_Data[[#This Row],[Rooms_Occupied]]/F11 -> 0.78571429 | H11: 1777 | I11: =Daily_Data[[#This Row],[Room_rate]]*Daily_Data[[#This Row],[Rooms_Occupied]] -> 19547 | J11: =Daily_Data[[#This Row],[Total_Sales]] * 0.22 -> 4300.34 | K11: =INDEX(Expense_master[Monthly_Rent],MATCH(Daily_Data[[#This Row],[Month_key]],Expense_master[Month_Key],0)) / INDEX(Expense_master[Days_in_Month],MATCH(Daily_Data[[#This Row],[Month_key]],Expense_master[Month_Key],0)) -> 6129.0323 | L11: =SUMIFS(Expense_master[Staff_Salary],Expense_master[Month_Key],Daily_Data[[#This Row],[Month_key]]) / SUMIFS(Expense_master[Days_in_Month],Expense_master[Month_Key],Daily_Data[[#This Row],[Month_key]]) -> 2258.0645 | M11: =Daily_Data[[#This Row],[Rooms_Occupied]] * (SUMIFS(Expense_master[Housekeeping_Laundy],Expense_master[Month_Key],Daily_Data[[#This Row],[Month_key]]) / SUMIFS(Occupancy_table[Monthly_rooms_Occupied],Occupancy_table[Month_Key],Daily_Data[[#This Row],[Month_key]])) -> 307.26257 | N11: =0.4 * (SUMIFS(Expense_master[Electicity_Bill],Expense_master[Month_Key],Daily_Data[[#This Row],[Month_key]]) / SUMIFS(Expense_master[Days_in_Month],Expense_master[Month_Key],Daily_Data[[#This Row],[Month_key]])) + Daily_Data[[#This Row],[Rooms_Occupied]] * ( (0.6 * SUMIFS(Expense_master[Electicity_Bill],Expense_master[Month_Key], Daily_Data[[#This Row],[Month_key]])) / SUMIFS(Occupancy_table[Monthly_rooms_Occupied],Occupancy_table[Month_Key],Daily_Data[[#This Row],[Month_key]])) -> 1651.9403 | O11: =SUMIFS(Expense_master[Monthly_Maintenance],Expense_master[Month_Key],Daily_Data[[#This Row],[Month_key]]) / SUMIFS(Expense_master[Days_in_Month],Expense_master[Month_Key], Daily_Data[[#This Row],[Month_key]]) -> 645.16129 | P11: =Daily_Data[[#This Row],[OTA Commision]] + Daily_Data[[#This Row],[Daily_Rent]]+Daily_Data[[#This Row],[Daily_Staff]]+Daily_Data[[#This Row],[Daily_HK]]+Daily_Data[[#This Row],[Daily_Electricity]] + Daily_Data[[#This Row],[Daily Maintenance]] -> 15291.801 | Q11: =Daily_Data[[#This Row],[Total_Sales]]-Daily_Data[[#This Row],[Total_Daily_Expense]] -> 4255.1991 | R11: =Daily_Data[[#This Row],[Total_Sales]]/Daily_Data[[#This Row],[Rooms_Occupied]] -> 1777 | S11: =Daily_Data[[#This Row],[Total_Sales]] / Daily_Data[[#This Row],[Max_rooms]] -> 1396.2143 | W11: Net Profit | X11: =SUM(Daily_Data[Profit]) -> 420821.66
A12: 44937 | B12: =DATE(YEAR(Daily_Data[[#This Row],[Date]]), MONTH(Daily_Data[[#This Row],[Date]]), 1) -> 44927 | C12: =TEXT(Daily_Data[[#This Row],[Month_key]],"mmmm") -> January | D12: =TEXT(Daily_Data[[#This Row],[Month_key]],"yyyy") -> 2023 | E12: 10 | F12: 14 | G12: =Daily_Data[[#This Row],[Rooms_Occupied]]/F12 -> 0.71428571 | H12: 1141 | I12: =Daily_Data[[#This Row],[Room_rate]]*Daily_Data[[#This Row],[Rooms_Occupied]] -> 11410 | J12: =Daily_Data[[#This Row],[Total_Sales]] * 0.22 -> 2510.2 | K12: =INDEX(Expense_master[Monthly_Rent],MATCH(Daily_Data[[#This Row],[Month_key]],Expense_master[Month_Key],0)) / INDEX(Expense_master[Days_in_Month],MATCH(Daily_Data[[#This Row],[Month_key]],Expense_master[Month_Key],0)) -> 6129.0323 | L12: =SUMIFS(Expense_master[Staff_Salary],Expense_master[Month_Key],Daily_Data[[#This Row],[Month_key]]) / SUMIFS(Expense_master[Days_in_Month],Expense_master[Month_Key],Daily_Data[[#This Row],[Month_key]]) -> 2258.0645 | M12: =Daily_Data[[#This Row],[Rooms_Occupied]] * (SUMIFS(Expense_master[Housekeeping_Laundy],Expense_master[Month_Key],Daily_Data[[#This Row],[Month_key]]) / SUMIFS(Occupancy_table[Monthly_rooms_Occupied],Occupancy_table[Month_Key],Daily_Data[[#This Row],[Month_key]])) -> 279.32961 | N12: =0.4 * (SUMIFS(Expense_master[Electicity_Bill],Expense_master[Month_Key],Daily_Data[[#This Row],[Month_key]]) / SUMIFS(Expense_master[Days_in_Month],Expense_master[Month_Key],Daily_Data[[#This Row],[Month_key]])) + Daily_Data[[#This Row],[Rooms_Occupied]] * ( (0.6 * SUMIFS(Expense_master[Electicity_Bill],Expense_master[Month_Key], Daily_Data[[#This Row],[Month_key]])) / SUMIFS(Occupancy_table[Monthly_rooms_Occupied],Occupancy_table[Month_Key],Daily_Data[[#This Row],[Month_key]])) -> 1563.5962 | O12: =SUMIFS(Expense_master[Monthly_Maintenance],Expense_master[Month_Key],Daily_Data[[#This Row],[Month_key]]) / SUMIFS(Expense_master[Days_in_Month],Expense_master[Month_Key], Daily_Data[[#This Row],[Month_key]]) -> 645.16129 | P12: =Daily_Data[[#This Row],[OTA Commision]] + Daily_Data[[#This Row],[Daily_Rent]]+Daily_Data[[#This Row],[Daily_Staff]]+Daily_Data[[#This Row],[Daily_HK]]+Daily_Data[[#This Row],[Daily_Electricity]] + Daily_Data[[#This Row],[Daily Maintenance]] -> 13385.384 | Q12: =Daily_Data[[#This Row],[Total_Sales]]-Daily_Data[[#This Row],[Total_Daily_Expense]] -> -1975.3839 | R12: =Daily_Data[[#This Row],[Total_Sales]]/Daily_Data[[#This Row],[Rooms_Occupied]] -> 1141 | S12: =Daily_Data[[#This Row],[Total_Sales]] / Daily_Data[[#This Row],[Max_rooms]] -> 815 | W12: Total Rooms Sold | X12: =SUM(Daily_Data[Rooms_Occupied]) -> 7974
A13: 44938 | B13: =DATE(YEAR(Daily_Data[[#This Row],[Date]]), MONTH(Daily_Data[[#This Row],[Date]]), 1) -> 44927 | C13: =TEXT(Daily_Data[[#This Row],[Month_key]],"mmmm") -> January | D13: =TEXT(Daily_Data[[#This Row],[Month_key]],"yyyy") -> 2023 | E13: 9 | F13: 14 | G13: =Daily_Data[[#This Row],[Rooms_Occupied]]/F13 -> 0.64285714 | H13: 1316 | I13: =Daily_Data[[#This Row],[Room_rate]]*Daily_Data[[#This Row],[Rooms_Occupied]] -> 11844 | J13: =Daily_Data[[#This Row],[Total_Sales]] * 0.22 -> 2605.68 | K13: =INDEX(Expense_master[Monthly_Rent],MATCH(Daily_Data[[#This Row],[Month_key]],Expense_master[Month_Key],0)) / INDEX(Expense_master[Days_in_Month],MATCH(Daily_Data[[#This Row],[Month_key]],Expense_master[Month_Key],0)) -> 6129.0323 | L13: =SUMIFS(Expense_master[Staff_Salary],Expense_master[Month_Key],Daily_Data[[#This Row],[Month_key]]) / SUMIFS(Expense_master[Days_in_Month],Expense_master[Month_Key],Daily_Data[[#This Row],[Month_key]]) -> 2258.0645 | M13: =Daily_Data[[#This Row],[Rooms_Occupied]] * (SUMIFS(Expense_master[Housekeeping_Laundy],Expense_master[Month_Key],Daily_Data[[#This Row],[Month_key]]) / SUMIFS(Occupancy_table[Monthly_rooms_Occupied],Occupancy_table[Month_Key],Daily_Data[[#This Row],[Month_key]])) -> 251.39665 | N13: =0.4 * (SUMIFS(Expense_master[Electicity_Bill],Expense_master[Month_Key],Daily_Data[[#This Row],[Month_key]]) / SUMIFS(Expense_master[Days_in_Month],Expense_master[Month_Key],Daily_Data[[#This Row],[Month_key]])) + Daily_Data[[#This Row],[Rooms_Occupied]] * ( (0.6 * SUMIFS(Expense_master[Electicity_Bill],Expense_master[Month_Key], Daily_Data[[#This Row],[Month_key]])) / SUMIFS(Occupancy_table[Monthly_rooms_Occupied],Occupancy_table[Month_Key],Daily_Data[[#This Row],[Month_key]])) -> 1475.252 | O13: =SUMIFS(Expense_master[Monthly_Maintenance],Expense_master[Month_Key],Daily_Data[[#This Row],[Month_key]]) / SUMIFS(Expense_master[Days_in_Month],Expense_master[Month_Key], Daily_Data[[#This Row],[Month_key]]) -> 645.16129 | P13: =Daily_Data[[#This Row],[OTA Commision]] + Daily_Data[[#This Row],[Daily_Rent]]+Daily_Data[[#This Row],[Daily_Staff]]+Daily_Data[[#This Row],[Daily_HK]]+Daily_Data[[#This Row],[Daily_Electricity]] + Daily_Data[[#This Row],[Daily Maintenance]] -> 13364.587 | Q13: =Daily_Data[[#This Row],[Total_Sales]]-Daily_Data[[#This Row],[Total_Daily_Expense]] -> -1520.5868 | R13: =Daily_Data[[#This Row],[Total_Sales]]/Daily_Data[[#This Row],[Rooms_Occupied]] -> 1316 | S13: =Daily_Data[[#This Row],[Total_Sales]] / Daily_Data[[#This Row],[Max_rooms]] -> 846 | W13: Average Occupancy | X13: =AVERAGE(Daily_Data[Occupancy_rate]) -> 0.77916748
A14: 44939 | B14: =DATE(YEAR(Daily_Data[[#This Row],[Date]]), MONTH(Daily_Data[[#This Row],[Date]]), 1) -> 44927 | C14: =TEXT(Daily_Data[[#This Row],[Month_key]],"mmmm") -> January | D14: =TEXT(Daily_Data[[#This Row],[Month_key]],"yyyy") -> 2023 | E14: 14 | F14: 14 | G14: =Daily_Data[[#This Row],[Rooms_Occupied]]/F14 -> 1 | H14: 1538 | I14: =Daily_Data[[#This Row],[Room_rate]]*Daily_Data[[#This Row],[Rooms_Occupied]] -> 21532 | J14: =Daily_Data[[#This Row],[Total_Sales]] * 0.22 -> 4737.04 | K14: =INDEX(Expense_master[Monthly_Rent],MATCH(Daily_Data[[#This Row],[Month_key]],Expense_master[Month_Key],0)) / INDEX(Expense_master[Days_in_Month],MATCH(Daily_Data[[#This Row],[Month_key]],Expense_master[Month_Key],0)) -> 6129.0323 | L14: =SUMIFS(Expense_master[Staff_Salary],Expense_master[Month_Key],Daily_Data[[#This Row],[Month_key]]) / SUMIFS(Expense_master[Days_in_Month],Expense_master[Month_Key],Daily_Data[[#This Row],[Month_key]]) -> 2258.0645 | M14: =Daily_Data[[#This Row],[Rooms_Occupied]] * (SUMIFS(Expense_master[Housekeeping_Laundy],Expense_master[Month_Key],Daily_Data[[#This Row],[Month_key]]) / SUMIFS(Occupancy_table[Monthly_rooms_Occupied],Occupancy_table[Month_Key],Daily_Data[[#This Row],[Month_key]])) -> 391.06145 | N14: =0.4 * (SUMIFS(Expense_master[Electicity_Bill],Expense_master[Month_Key],Daily_Data[[#This Row],[Month_key]]) / SUMIFS(Expense_master[Days_in_Month],Expense_master[Month_Key],Daily_Data[[#This Row],[Month_key]])) + Daily_Data[[#This Row],[Rooms_Occupied]] * ( (0.6 * SUMIFS(Expense_master[Electicity_Bill],Expense_master[Month_Key], Daily_Data[[#This Row],[Month_key]])) / SUMIFS(Occupancy_table[Monthly_rooms_Occupied],Occupancy_table[Month_Key],Daily_Data[[#This Row],[Month_key]])) -> 1916.9727 | O14: =SUMIFS(Expense_master[Monthly_Maintenance],Expense_master[Month_Key],Daily_Data[[#This Row],[Month_key]]) / SUMIFS(Expense_master[Days_in_Month],Expense_master[Month_Key], Daily_Data[[#This Row],[Month_key]]) -> 645.16129 | P14: =Daily_Data[[#This Row],[OTA Commision]] + Daily_Data[[#This Row],[Daily_Rent]]+Daily_Data[[#This Row],[Daily_Staff]]+Daily_Data[[#This Row],[Daily_HK]]+Daily_Data[[#This Row],[Daily_Electricity]] + Daily_Data[[#This Row],[Daily Maintenance]] -> 16077.332 | Q14: =Daily_Data[[#This Row],[Total_Sales]]-Daily_Data[[#This Row],[Total_Daily_Expense]] -> 5454.6678 | R14: =Daily_Data[[#This Row],[Total_Sales]]/Daily_Data[[#This Row],[Rooms_Occupied]] -> 1538 | S14: =Daily_Data[[#This Row],[Total_Sales]] / Daily_Data[[#This Row],[Max_rooms]] -> 1538 | W14: Average RevPar | X14: =AVERAGE(Daily_Data[RevPar]) -> 1176.0892
A15: 44940 | B15: =DATE(YEAR(Daily_Data[[#This Row],[Date]]), MONTH(Daily_Data[[#This Row],[Date]]), 1) -> 44927 | C15: =TEXT(Daily_Data[[#This Row],[Month_key]],"mmmm") -> January | D15: =TEXT(Daily_Data[[#This Row],[Month_key]],"yyyy") -> 2023 | E15: 11 | F15: 14 | G15: =Daily_Data[[#This Row],[Rooms_Occupied]]/F15 -> 0.78571429 | H15: 1191 | I15: =Daily_Data[[#This Row],[Room_rate]]*Daily_Data[[#This Row],[Rooms_Occupied]] -> 13101 | J15: =Daily_Data[[#This Row],[Total_Sales]] * 0.22 -> 2882.22 | K15: =INDEX(Expense_master[Monthly_Rent],MATCH(Daily_Data[[#This Row],[Month_key]],Expense_master[Month_Key],0)) / INDEX(Expense_master[Days_in_Month],MATCH(Daily_Data[[#This Row],[Month_key]],Expense_master[Month_Key],0)) -> 6129.0323 | L15: =SUMIFS(Expense_master[Staff_Salary],Expense_master[Month_Key],Daily_Data[[#This Row],[Month_key]]) / SUMIFS(Expense_master[Days_in_Month],Expense_master[Month_Key],Daily_Data[[#This Row],[Month_key]]) -> 2258.0645 | M15: =Daily_Data[[#This Row],[Rooms_Occupied]] * (SUMIFS(Expense_master[Housekeeping_Laundy],Expense_master[Month_Key],Daily_Data[[#This Row],[Month_key]]) / SUMIFS(Occupancy_table[Monthly_rooms_Occupied],Occupancy_table[Month_Key],Daily_Data[[#This Row],[Month_key]])) -> 307.26257 | N15: =0.4 * (SUMIFS(Expense_master[Electicity_Bill],Expense_master[Month_Key],Daily_Data[[#This Row],[Month_key]]) / SUMIFS(Expense_master[Days_in_Month],Expense_master[Month_Key],Daily_Data[[#This Row],[Month_key]])) + Daily_Data[[#This Row],[Rooms_Occupied]] * ( (0.6 * SUMIFS(Expense_master[Electicity_Bill],Expense_master[Month_Key], Daily_Data[[#This Row],[Month_key]])) / SUMIFS(Occupancy_table[Monthly_rooms_Occupied],Occupancy_table[Month_Key],Daily_Data[[#This Row],[Month_key]])) -> 1651.9403 | O15: =SUMIFS(Expense_master[Monthly_Maintenance],Expense_master[Month_Key],Daily_Data[[#This Row],[Month_key]]) / SUMIFS(Expense_master[Days_in_Month],Expense_master[Month_Key], Daily_Data[[#This Row],[Month_key]]) -> 645.16129 | P15: =Daily_Data[[#This Row],[OTA Commision]] + Daily_Data[[#This Row],[Daily_Rent]]+Daily_Data[[#This Row],[Daily_Staff]]+Daily_Data[[#This Row],[Daily_HK]]+Daily_Data[[#This Row],[Daily_Electricity]] + Daily_Data[[#This Row],[Daily Maintenance]] -> 13873.681 | Q15: =Daily_Data[[#This Row],[Total_Sales]]-Daily_Data[[#This Row],[Total_Daily_Expense]] -> -772.68095 | R15: =Daily_Data[[#This Row],[Total_Sales]]/Daily_Data[[#This Row],[Rooms_Occupied]] -> 1191 | S15: =Daily_Data[[#This Row],[Total_Sales]] / Daily_Data[[#This Row],[Max_rooms]] -> 935.78571 | W15: Total Expense | X15: =SUM(Daily_Data[Total_Daily_Expense]) -> 11615275
A16: 44941 | B16: =DATE(YEAR(Daily_Data[[#This Row],[Date]]), MONTH(Daily_Data[[#This Row],[Date]]), 1) -> 44927 | C16: =TEXT(Daily_Data[[#This Row],[Month_key]],"mmmm") -> January | D16: =TEXT(Daily_Data[[#This Row],[Month_key]],"yyyy") -> 2023 | E16: 8 | F16: 14 | G16: =Daily_Data[[#This Row],[Rooms_Occupied]]/F16 -> 0.57142857 | H16: 1864 | I16: =Daily_Data[[#This Row],[Room_rate]]*Daily_Data[[#This Row],[Rooms_Occupied]] -> 14912 | J16: =Daily_Data[[#This Row],[Total_Sales]] * 0.22 -> 3280.64 | K16: =INDEX(Expense_master[Monthly_Rent],MATCH(Daily_Data[[#This Row],[Month_key]],Expense_master[Month_Key],0)) / INDEX(Expense_master[Days_in_Month],MATCH(Daily_Data[[#This Row],[Month_key]],Expense_master[Month_Key],0)) -> 6129.0323 | L16: =SUMIFS(Expense_master[Staff_Salary],Expense_master[Month_Key],Daily_Data[[#This Row],[Month_key]]) / SUMIFS(Expense_master[Days_in_Month],Expense_master[Month_Key],Daily_Data[[#This Row],[Month_key]]) -> 2258.0645 | M16: =Daily_Data[[#This Row],[Rooms_Occupied]] * (SUMIFS(Expense_master[Housekeeping_Laundy],Expense_master[Month_Key],Daily_Data[[#This Row],[Month_key]]) / SUMIFS(Occupancy_table[Monthly_rooms_Occupied],Occupancy_table[Month_Key],Daily_Data[[#This Row],[Month_key]])) -> 223.46369 | N16: =0.4 * (SUMIFS(Expense_master[Electicity_Bill],Expense_master[Month_Key],Daily_Data[[#This Row],[Month_key]]) / SUMIFS(Expense_master[Days_in_Month],Expense_master[Month_Key],Daily_Data[[#This Row],[Month_key]])) + Daily_Data[[#This Row],[Rooms_Occupied]] * ( (0.6 * SUMIFS(Expense_master[Electicity_Bill],Expense_master[Month_Key], Daily_Data[[#This Row],[Month_key]])) / SUMIFS(Occupancy_table[Monthly_rooms_Occupied],Occupancy_table[Month_Key],Daily_Data[[#This Row],[Month_key]])) -> 1386.9079 | O16: =SUMIFS(Expense_master[Monthly_Maintenance],Expense_master[Month_Key],Daily_Data[[#This Row],[Month_key]]) / SUMIFS(Expense_master[Days_in_Month],Expense_master[Month_Key], Daily_Data[[#This Row],[Month_key]]) -> 645.16129 | P16: =Daily_Data[[#This Row],[OTA Commision]] + Daily_Data[[#This Row],[Daily_Rent]]+Daily_Data[[#This Row],[Daily_Staff]]+Daily_Data[[#This Row],[Daily_HK]]+Daily_Data[[#This Row],[Daily_Electricity]] + Daily_Data[[#This Row],[Daily Maintenance]] -> 13923.27 | Q16: =Daily_Data[[#This Row],[Total_Sales]]-Daily_Data[[#This Row],[Total_Daily_Expense]] -> 988.73034 | R16: =Daily_Data[[#This Row],[Total_Sales]]/Daily_Data[[#This Row],[Rooms_Occupied]] -> 1864 | S16: =Daily_Data[[#This Row],[Total_Sales]] / Daily_Data[[#This Row],[Max_rooms]] -> 1065.1429 | W16: OTA Commission | X16: =Daily_Data[OTA Commision] / Daily_Data[Total_Sales] -> 0.22
A17: 44942 | B17: =DATE(YEAR(Daily_Data[[#This Row],[Date]]), MONTH(Daily_Data[[#This Row],[Date]]), 1) -> 44927 | C17: =TEXT(Daily_Data[[#This Row],[Month_key]],"mmmm") -> January | D17: =TEXT(Daily_Data[[#This Row],[Month_key]],"yyyy") -> 2023 | E17: 13 | F17: 14 | G17: =Daily_Data[[#This Row],[Rooms_Occupied]]/F17 -> 0.92857143 | H17: 1479 | I17: =Daily_Data[[#This Row],[Room_rate]]*Daily_Data[[#This Row],[Rooms_Occupied]] -> 19227 | J17: =Daily_Data[[#This Row],[Total_Sales]] * 0.22 -> 4229.94 | K17: =INDEX(Expense_master[Monthly_Rent],MATCH(Daily_Data[[#This Row],[Month_key]],Expense_master[Month_Key],0)) / INDEX(Expense_master[Days_in_Month],MATCH(Daily_Data[[#This Row],[Month_key]],Expense_master[Month_Key],0)) -> 6129.0323 | L17: =SUMIFS(Expense_master[Staff_Salary],Expense_master[Month_Key],Daily_Data[[#This Row],[Month_key]]) / SUMIFS(Expense_master[Days_in_Month],Expense_master[Month_Key],Daily_Data[[#This Row],[Month_key]]) -> 2258.0645 | M17: =Daily_Data[[#This Row],[Rooms_Occupied]] * (SUMIFS(Expense_master[Housekeeping_Laundy],Expense_master[Month_Key],Daily_Data[[#This Row],[Month_key]]) / SUMIFS(Occupancy_table[Monthly_rooms_Occupied],Occupancy_table[Month_Key],Daily_Data[[#This Row],[Month_key]])) -> 363.12849 | N17: =0.4 * (SUMIFS(Expense_master[Electicity_Bill],Expense_master[Month_Key],Daily_Data[[#This Row],[Month_key]]) / SUMIFS(Expense_master[Days_in_Month],Expense_master[Month_Key],Daily_Data[[#This Row],[Month_key]])) + Daily_Data[[#This Row],[Rooms_Occupied]] * ( (0.6 * SUMIFS(Expense_master[Electicity_Bill],Expense_master[Month_Key], Daily_Data[[#This Row],[Month_key]])) / SUMIFS(Occupancy_table[Monthly_rooms_Occupied],Occupancy_table[Month_Key],Daily_Data[[#This Row],[Month_key]])) -> 1828.6286 | O17: =SUMIFS(Expense_master[Monthly_Maintenance],Expense_master[Month_Key],Daily_Data[[#This Row],[Month_key]]) / SUMIFS(Expense_master[Days_in_Month],Expense_master[Month_Key], Daily_Data[[#This Row],[Month_key]]) -> 645.16129 | P17: =Daily_Data[[#This Row],[OTA Commision]] + Daily_Data[[#This Row],[Daily_Rent]]+Daily_Data[[#This Row],[Daily_Staff]]+Daily_Data[[#This Row],[Daily_HK]]+Daily_Data[[#This Row],[Daily_Electricity]] + Daily_Data[[#This Row],[Daily Maintenance]] -> 15453.955 | Q17: =Daily_Data[[#This Row],[Total_Sales]]-Daily_Data[[#This Row],[Total_Daily_Expense]] -> 3773.0449 | R17: =Daily_Data[[#This Row],[Total_Sales]]/Daily_Data[[#This Row],[Rooms_Occupied]] -> 1479 | S17: =Daily_Data[[#This Row],[Total_Sales]] / Daily_Data[[#This Row],[Max_rooms]] -> 1373.3571 | W17: Highest Revenue Month
A18: 44943 | B18: =DATE(YEAR(Daily_Data[[#This Row],[Date]]), MONTH(Daily_Data[[#This Row],[Date]]), 1) -> 44927 | C18: =TEXT(Daily_Data[[#This Row],[Month_key]],"mmmm") -> January | D18: =TEXT(Daily_Data[[#This Row],[Month_key]],"yyyy") -> 2023 | E18: 10 | F18: 14 | G18: =Daily_Data[[#This Row],[Rooms_Occupied]]/F18 -> 0.71428571 | H18: 1513 | I18: =Daily_Data[[#This Row],[Room_rate]]*Daily_Data[[#This Row],[Rooms_Occupied]] -> 15130 | J18: =Daily_Data[[#This Row],[Total_Sales]] * 0.22 -> 3328.6 | K18: =INDEX(Expense_master[Monthly_Rent],MATCH(Daily_Data[[#This Row],[Month_key]],Expense_master[Month_Key],0)) / INDEX(Expense_master[Days_in_Month],MATCH(Daily_Data[[#This Row],[Month_key]],Expense_master[Month_Key],0)) -> 6129.0323 | L18: =SUMIFS(Expense_master[Staff_Salary],Expense_master[Month_Key],Daily_Data[[#This Row],[Month_key]]) / SUMIFS(Expense_master[Days_in_Month],Expense_master[Month_Key],Daily_Data[[#This Row],[Month_key]]) -> 2258.0645 | M18: =Daily_Data[[#This Row],[Rooms_Occupied]] * (SUMIFS(Expense_master[Housekeeping_Laundy],Expense_master[Month_Key],Daily_Data[[#This Row],[Month_key]]) / SUMIFS(Occupancy_table[Monthly_rooms_Occupied],Occupancy_table[Month_Key],Daily_Data[[#This Row],[Month_key]])) -> 279.32961 | N18: =0.4 * (SUMIFS(Expense_master[Electicity_Bill],Expense_master[Month_Key],Daily_Data[[#This Row],[Month_key]]) / SUMIFS(Expense_master[Days_in_Month],Expense_master[Month_Key],Daily_Data[[#This Row],[Month_key]])) + Daily_Data[[#This Row],[Rooms_Occupied]] * ( (0.6 * SUMIFS(Expense_master[Electicity_Bill],Expense_master[Month_Key], Daily_Data[[#This Row],[Month_key]])) / SUMIFS(Occupancy_table[Monthly_rooms_Occupied],Occupancy_table[Month_Key],Daily_Data[[#This Row],[Month_key]])) -> 1563.5962 | O18: =SUMIFS(Expense_master[Monthly_Maintenance],Expense_master[Month_Key],Daily_Data[[#This Row],[Month_key]]) / SUMIFS(Expense_master[Days_in_Month],Expense_master[Month_Key], Daily_Data[[#This Row],[Month_key]]) -> 645.16129 | P18: =Daily_Data[[#This Row],[OTA Commision]] + Daily_Data[[#This Row],[Daily_Rent]]+Daily_Data[[#This Row],[Daily_Staff]]+Daily_Data[[#This Row],[Daily_HK]]+Daily_Data[[#This Row],[Daily_Electricity]] + Daily_Data[[#This Row],[Daily Maintenance]] -> 14203.784 | Q18: =Daily_Data[[#This Row],[Total_Sales]]-Daily_Data[[#This Row],[Total_Daily_Expense]] -> 926.21615 | R18: =Daily_Data[[#This Row],[Total_Sales]]/Daily_Data[[#This Row],[Rooms_Occupied]] -> 1513 | S18: =Daily_Data[[#This Row],[Total_Sales]] / Daily_Data[[#This Row],[Max_rooms]] -> 1080.7143 | W18: Lowest Revenue Month
A19: 44944 | B19: =DATE(YEAR(Daily_Data[[#This Row],[Date]]), MONTH(Daily_Data[[#This Row],[Date]]), 1) -> 44927 | C19: =TEXT(Daily_Data[[#This Row],[Month_key]],"mmmm") -> January | D19: =TEXT(Daily_Data[[#This Row],[Month_key]],"yyyy") -> 2023 | E19: 10 | F19: 14 | G19: =Daily_Data[[#This Row],[Rooms_Occupied]]/F19 -> 0.71428571 | H19: 1577 | I19: =Daily_Data[[#This Row],[Room_rate]]*Daily_Data[[#This Row],[Rooms_Occupied]] -> 15770 | J19: =Daily_Data[[#This Row],[Total_Sales]] * 0.22 -> 3469.4 | K19: =INDEX(Expense_master[Monthly_Rent],MATCH(Daily_Data[[#This Row],[Month_key]],Expense_master[Month_Key],0)) / INDEX(Expense_master[Days_in_Month],MATCH(Daily_Data[[#This Row],[Month_key]],Expense_master[Month_Key],0)) -> 6129.0323 | L19: =SUMIFS(Expense_master[Staff_Salary],Expense_master[Month_Key],Daily_Data[[#This Row],[Month_key]]) / SUMIFS(Expense_master[Days_in_Month],Expense_master[Month_Key],Daily_Data[[#This Row],[Month_key]]) -> 2258.0645 | M19: =Daily_Data[[#This Row],[Rooms_Occupied]] * (SUMIFS(Expense_master[Housekeeping_Laundy],Expense_master[Month_Key],Daily_Data[[#This Row],[Month_key]]) / SUMIFS(Occupancy_table[Monthly_rooms_Occupied],Occupancy_table[Month_Key],Daily_Data[[#This Row],[Month_key]])) -> 279.32961 | N19: =0.4 * (SUMIFS(Expense_master[Electicity_Bill],Expense_master[Month_Key],Daily_Data[[#This Row],[Month_key]]) / SUMIFS(Expense_master[Days_in_Month],Expense_master[Month_Key],Daily_Data[[#This Row],[Month_key]])) + Daily_Data[[#This Row],[Rooms_Occupied]] * ( (0.6 * SUMIFS(Expense_master[Electicity_Bill],Expense_master[Month_Key], Daily_Data[[#This Row],[Month_key]])) / SUMIFS(Occupancy_table[Monthly_rooms_Occupied],Occupancy_table[Month_Key],Daily_Data[[#This Row],[Month_key]])) -> 1563.5962 | O19: =SUMIFS(Expense_master[Monthly_Maintenance],Expense_master[Month_Key],Daily_Data[[#This Row],[Month_key]]) / SUMIFS(Expense_master[Days_in_Month],Expense_master[Month_Key], Daily_Data[[#This Row],[Month_key]]) -> 645.16129 | P19: =Daily_Data[[#This Row],[OTA Commision]] + Daily_Data[[#This Row],[Daily_Rent]]+Daily_Data[[#This Row],[Daily_Staff]]+Daily_Data[[#This Row],[Daily_HK]]+Daily_Data[[#This Row],[Daily_Electricity]] + Daily_Data[[#This Row],[Daily Maintenance]] -> 14344.584 | Q19: =Daily_Data[[#This Row],[Total_Sales]]-Daily_Data[[#This Row],[Total_Daily_Expense]] -> 1425.4161 | R19: =Daily_Data[[#This Row],[Total_Sales]]/Daily_Data[[#This Row],[Rooms_Occupied]] -> 1577 | S19: =Daily_Data[[#This Row],[Total_Sales]] / Daily_Data[[#This Row],[Max_rooms]] -> 1126.4286 | W19: highest RevPar grwoth %
A20: 44945 | B20: =DATE(YEAR(Daily_Data[[#This Row],[Date]]), MONTH(Daily_Data[[#This Row],[Date]]), 1) -> 44927 | C20: =TEXT(Daily_Data[[#This Row],[Month_key]],"mmmm") -> January | D20: =TEXT(Daily_Data[[#This Row],[Month_key]],"yyyy") -> 2023 | E20: 10 | F20: 14 | G20: =Daily_Data[[#This Row],[Rooms_Occupied]]/F20 -> 0.71428571 | H20: 1282 | I20: =Daily_Data[[#This Row],[Room_rate]]*Daily_Data[[#This Row],[Rooms_Occupied]] -> 12820 | J20: =Daily_Data[[#This Row],[Total_Sales]] * 0.22 -> 2820.4 | K20: =INDEX(Expense_master[Monthly_Rent],MATCH(Daily_Data[[#This Row],[Month_key]],Expense_master[Month_Key],0)) / INDEX(Expense_master[Days_in_Month],MATCH(Daily_Data[[#This Row],[Month_key]],Expense_master[Month_Key],0)) -> 6129.0323 | L20: =SUMIFS(Expense_master[Staff_Salary],Expense_master[Month_Key],Daily_Data[[#This Row],[Month_key]]) / SUMIFS(Expense_master[Days_in_Month],Expense_master[Month_Key],Daily_Data[[#This Row],[Month_key]]) -> 2258.0645 | M20: =Daily_Data[[#This Row],[Rooms_Occupied]] * (SUMIFS(Expense_master[Housekeeping_Laundy],Expense_master[Month_Key],Daily_Data[[#This Row],[Month_key]]) / SUMIFS(Occupancy_table[Monthly_rooms_Occupied],Occupancy_table[Month_Key],Daily_Data[[#This Row],[Month_key]])) -> 279.32961 | N20: =0.4 * (SUMIFS(Expense_master[Electicity_Bill],Expense_master[Month_Key],Daily_Data[[#This Row],[Month_key]]) / SUMIFS(Expense_master[Days_in_Month],Expense_master[Month_Key],Daily_Data[[#This Row],[Month_key]])) + Daily_Data[[#This Row],[Rooms_Occupied]] * ( (0.6 * SUMIFS(Expense_master[Electicity_Bill],Expense_master[Month_Key], Daily_Data[[#This Row],[Month_key]])) / SUMIFS(Occupancy_table[Monthly_rooms_Occupied],Occupancy_table[Month_Key],Daily_Data[[#This Row],[Month_key]])) -> 1563.5962 | O20: =SUMIFS(Expense_master[Monthly_Maintenance],Expense_master[Month_Key],Daily_Data[[#This Row],[Month_key]]) / SUMIFS(Expense_master[Days_in_Month],Expense_master[Month_Key], Daily_Data[[#This Row],[Month_key]]) -> 645.16129 | P20: =Daily_Data[[#This Row],[OTA Commision]] + Daily_Data[[#This Row],[Daily_Rent]]+Daily_Data[[#This Row],[Daily_Staff]]+Daily_Data[[#This Row],[Daily_HK]]+Daily_Data[[#This Row],[Daily_Electricity]] + Daily_Data[[#This Row],[Daily Maintenance]] -> 13695.584 | Q20: =Daily_Data[[#This Row],[Total_Sales]]-Daily_Data[[#This Row],[Total_Daily_Expense]] -> -875.58385 | R20: =Daily_Data[[#This Row],[Total_Sales]]/Daily_Data[[#This Row],[Rooms_Occupied]] -> 1282 | S20: =Daily_Data[[#This Row],[Total_Sales]] / Daily_Data[[#This Row],[Max_rooms]] -> 915.71429 | W20: CPOR | X20: =Daily_Data[Total_Daily_Expense] / Daily_Data[Rooms_Occupied] -> 1369.5584
A21: 44946 | B21: =DATE(YEAR(Daily_Data[[#This Row],[Date]]), MONTH(Daily_Data[[#This Row],[Date]]), 1) -> 44927 | C21: =TEXT(Daily_Data[[#This Row],[Month_key]],"mmmm") -> January | D21: =TEXT(Daily_Data[[#This Row],[Month_key]],"yyyy") -> 2023 | E21: 9 | F21: 14 | G21: =Daily_Data[[#This Row],[Rooms_Occupied]]/F21 -> 0.64285714 | H21: 1339 | I21: =Daily_Data[[#This Row],[Room_rate]]*Daily_Data[[#This Row],[Rooms_Occupied]] -> 12051 | J21: =Daily_Data[[#This Row],[Total_Sales]] * 0.22 -> 2651.22 | K21: =INDEX(Expense_master[Monthly_Rent],MATCH(Daily_Data[[#This Row],[Month_key]],Expense_master[Month_Key],0)) / INDEX(Expense_master[Days_in_Month],MATCH(Daily_Data[[#This Row],[Month_key]],Expense_master[Month_Key],0)) -> 6129.0323 | L21: =SUMIFS(Expense_master[Staff_Salary],Expense_master[Month_Key],Daily_Data[[#This Row],[Month_key]]) / SUMIFS(Expense_master[Days_in_Month],Expense_master[Month_Key],Daily_Data[[#This Row],[Month_key]]) -> 2258.0645 | M21: =Daily_Data[[#This Row],[Rooms_Occupied]] * (SUMIFS(Expense_master[Housekeeping_Laundy],Expense_master[Month_Key],Daily_Data[[#This Row],[Month_key]]) / SUMIFS(Occupancy_table[Monthly_rooms_Occupied],Occupancy_table[Month_Key],Daily_Data[[#This Row],[Month_key]])) -> 251.39665 | N21: =0.4 * (SUMIFS(Expense_master[Electicity_Bill],Expense_master[Month_Key],Daily_Data[[#This Row],[Month_key]]) / SUMIFS(Expense_master[Days_in_Month],Expense_master[Month_Key],Daily_Data[[#This Row],[Month_key]])) + Daily_Data[[#This Row],[Rooms_Occupied]] * ( (0.6 * SUMIFS(Expense_master[Electicity_Bill],Expense_master[Month_Key], Daily_Data[[#This Row],[Month_key]])) / SUMIFS(Occupancy_table[Monthly_rooms_Occupied],Occupancy_table[Month_Key],Daily_Data[[#This Row],[Month_key]])) -> 1475.252 | O21: =SUMIFS(Expense_master[Monthly_Maintenance],Expense_master[Month_Key],Daily_Data[[#This Row],[Month_key]]) / SUMIFS(Expense_master[Days_in_Month],Expense_master[Month_Key], Daily_Data[[#This Row],[Month_key]]) -> 645.16129 | P21: =Daily_Data[[#This Row],[OTA Commision]] + Daily_Data[[#This Row],[Daily_Rent]]+Daily_Data[[#This Row],[Daily_Staff]]+Daily_Data[[#This Row],[Daily_HK]]+Daily_Data[[#This Row],[Daily_Electricity]] + Daily_Data[[#This Row],[Daily Maintenance]] -> 13410.127 | Q21: =Daily_Data[[#This Row],[Total_Sales]]-Daily_Data[[#This Row],[Total_Daily_Expense]] -> -1359.1268 | R21: =Daily_Data[[#This Row],[Total_Sales]]/Daily_Data[[#This Row],[Rooms_Occupied]] -> 1339 | S21: =Daily_Data[[#This Row],[Total_Sales]] / Daily_Data[[#This Row],[Max_rooms]] -> 860.78571
A22: 44947 | B22: =DATE(YEAR(Daily_Data[[#This Row],[Date]]), MONTH(Daily_Data[[#This Row],[Date]]), 1) -> 44927 | C22: =TEXT(Daily_Data[[#This Row],[Month_key]],"mmmm") -> January | D22: =TEXT(Daily_Data[[#This Row],[Month_key]],"yyyy") -> 2023 | E22: 14 | F22: 14 | G22: =Daily_Data[[#This Row],[Rooms_Occupied]]/F22 -> 1 | H22: 1405 | I22: =Daily_Data[[#This Row],[Room_rate]]*Daily_Data[[#This Row],[Rooms_Occupied]] -> 19670 | J22: =Daily_Data[[#This Row],[Total_Sales]] * 0.22 -> 4327.4 | K22: =INDEX(Expense_master[Monthly_Rent],MATCH(Daily_Data[[#This Row],[Month_key]],Expense_master[Month_Key],0)) / INDEX(Expense_master[Days_in_Month],MATCH(Daily_Data[[#This Row],[Month_key]],Expense_master[Month_Key],0)) -> 6129.0323 | L22: =SUMIFS(Expense_master[Staff_Salary],Expense_master[Month_Key],Daily_Data[[#This Row],[Month_key]]) / SUMIFS(Expense_master[Days_in_Month],Expense_master[Month_Key],Daily_Data[[#This Row],[Month_key]]) -> 2258.0645 | M22: =Daily_Data[[#This Row],[Rooms_Occupied]] * (SUMIFS(Expense_master[Housekeeping_Laundy],Expense_master[Month_Key],Daily_Data[[#This Row],[Month_key]]) / SUMIFS(Occupancy_table[Monthly_rooms_Occupied],Occupancy_table[Month_Key],Daily_Data[[#This Row],[Month_key]])) -> 391.06145 | N22: =0.4 * (SUMIFS(Expense_master[Electicity_Bill],Expense_master[Month_Key],Daily_Data[[#This Row],[Month_key]]) / SUMIFS(Expense_master[Days_in_Month],Expense_master[Month_Key],Daily_Data[[#This Row],[Month_key]])) + Daily_Data[[#This Row],[Rooms_Occupied]] * ( (0.6 * SUMIFS(Expense_master[Electicity_Bill],Expense_master[Month_Key], Daily_Data[[#This Row],[Month_key]])) / SUMIFS(Occupancy_table[Monthly_rooms_Occupied],Occupancy_table[Month_Key],Daily_Data[[#This Row],[Month_key]])) -> 1916.9727 | O22: =SUMIFS(Expense_master[Monthly_Maintenance],Expense_master[Month_Key],Daily_Data[[#This Row],[Month_key]]) / SUMIFS(Expense_master[Days_in_Month],Expense_master[Month_Key], Daily_Data[[#This Row],[Month_key]]) -> 645.16129 | P22: =Daily_Data[[#This Row],[OTA Commision]] + Daily_Data[[#This Row],[Daily_Rent]]+Daily_Data[[#This Row],[Daily_Staff]]+Daily_Data[[#This Row],[Daily_HK]]+Daily_Data[[#This Row],[Daily_Electricity]] + Daily_Data[[#This Row],[Daily Maintenance]] -> 15667.692 | Q22: =Daily_Data[[#This Row],[Total_Sales]]-Daily_Data[[#This Row],[Total_Daily_Expense]] -> 4002.3078 | R22: =Daily_Data[[#This Row],[Total_Sales]]/Daily_Data[[#This Row],[Rooms_Occupied]] -> 1405 | S22: =Daily_Data[[#This Row],[Total_Sales]] / Daily_Data[[#This Row],[Max_rooms]] -> 1405
A23: 44948 | B23: =DATE(YEAR(Daily_Data[[#This Row],[Date]]), MONTH(Daily_Data[[#This Row],[Date]]), 1) -> 44927 | C23: =TEXT(Daily_Data[[#This Row],[Month_key]],"mmmm") -> January | D23: =TEXT(Daily_Data[[#This Row],[Month_key]],"yyyy") -> 2023 | E23: 14 | F23: 14 | G23: =Daily_Data[[#This Row],[Rooms_Occupied]]/F23 -> 1 | H23: 1513 | I23: =Daily_Data[[#This Row],[Room_rate]]*Daily_Data[[#This Row],[Rooms_Occupied]] -> 21182 | J23: =Daily_Data[[#This Row],[Total_Sales]] * 0.22 -> 4660.04 | K23: =INDEX(Expense_master[Monthly_Rent],MATCH(Daily_Data[[#This Row],[Month_key]],Expense_master[Month_Key],0)) / INDEX(Expense_master[Days_in_Month],MATCH(Daily_Data[[#This Row],[Month_key]],Expense_master[Month_Key],0)) -> 6129.0323 | L23: =SUMIFS(Expense_master[Staff_Salary],Expense_master[Month_Key],Daily_Data[[#This Row],[Month_key]]) / SUMIFS(Expense_master[Days_in_Month],Expense_master[Month_Key],Daily_Data[[#This Row],[Month_key]]) -> 2258.0645 | M23: =Daily_Data[[#This Row],[Rooms_Occupied]] * (SUMIFS(Expense_master[Housekeeping_Laundy],Expense_master[Month_Key],Daily_Data[[#This Row],[Month_key]]) / SUMIFS(Occupancy_table[Monthly_rooms_Occupied],Occupancy_table[Month_Key],Daily_Data[[#This Row],[Month_key]])) -> 391.06145 | N23: =0.4 * (SUMIFS(Expense_master[Electicity_Bill],Expense_master[Month_Key],Daily_Data[[#This Row],[Month_key]]) / SUMIFS(Expense_master[Days_in_Month],Expense_master[Month_Key],Daily_Data[[#This Row],[Month_key]])) + Daily_Data[[#This Row],[Rooms_Occupied]] * ( (0.6 * SUMIFS(Expense_master[Electicity_Bill],Expense_master[Month_Key], Daily_Data[[#This Row],[Month_key]])) / SUMIFS(Occupancy_table[Monthly_rooms_Occupied],Occupancy_table[Month_Key],Daily_Data[[#This Row],[Month_key]])) -> 1916.9727 | O23: =SUMIFS(Expense_master[Monthly_Maintenance],Expense_master[Month_Key],Daily_Data[[#This Row],[Month_key]]) / SUMIFS(Expense_master[Days_in_Month],Expense_master[Month_Key], Daily_Data[[#This Row],[Month_key]]) -> 645.16129 | P23: =Daily_Data[[#This Row],[OTA Commision]] + Daily_Data[[#This Row],[Daily_Rent]]+Daily_Data[[#This Row],[Daily_Staff]]+Daily_Data[[#This Row],[Daily_HK]]+Daily_Data[[#This Row],[Daily_Electricity]] + Daily_Data[[#This Row],[Daily Maintenance]] -> 16000.332 | Q23: =Daily_Data[[#This Row],[Total_Sales]]-Daily_Data[[#This Row],[Total_Daily_Expense]] -> 5181.6678 | R23: =Daily_Data[[#This Row],[Total_Sales]]/Daily_Data[[#This Row],[Rooms_Occupied]] -> 1513 | S23: =Daily_Data[[#This Row],[Total_Sales]] / Daily_Data[[#This Row],[Max_rooms]] -> 1513
A24: 44949 | B24: =DATE(YEAR(Daily_Data[[#This Row],[Date]]), MONTH(Daily_Data[[#This Row],[Date]]), 1) -> 44927 | C24: =TEXT(Daily_Data[[#This Row],[Month_key]],"mmmm") -> January | D24: =TEXT(Daily_Data[[#This Row],[Month_key]],"yyyy") -> 2023 | E24: 12 | F24: 14 | G24: =Daily_Data[[#This Row],[Rooms_Occupied]]/F24 -> 0.85714286 | H24: 1563 | I24: =Daily_Data[[#This Row],[Room_rate]]*Daily_Data[[#This Row],[Rooms_Occupied]] -> 18756 | J24: =Daily_Data[[#This Row],[Total_Sales]] * 0.22 -> 4126.32 | K24: =INDEX(Expense_master[Monthly_Rent],MATCH(Daily_Data[[#This Row],[Month_key]],Expense_master[Month_Key],0)) / INDEX(Expense_master[Days_in_Month],MATCH(Daily_Data[[#This Row],[Month_key]],Expense_master[Month_Key],0)) -> 6129.0323 | L24: =SUMIFS(Expense_master[Staff_Salary],Expense_master[Month_Key],Daily_Data[[#This Row],[Month_key]]) / SUMIFS(Expense_master[Days_in_Month],Expense_master[Month_Key],Daily_Data[[#This Row],[Month_key]]) -> 2258.0645 | M24: =Daily_Data[[#This Row],[Rooms_Occupied]] * (SUMIFS(Expense_master[Housekeeping_Laundy],Expense_master[Month_Key],Daily_Data[[#This Row],[Month_key]]) / SUMIFS(Occupancy_table[Monthly_rooms_Occupied],Occupancy_table[Month_Key],Daily_Data[[#This Row],[Month_key]])) -> 335.19553 | N24: =0.4 * (SUMIFS(Expense_master[Electicity_Bill],Expense_master[Month_Key],Daily_Data[[#This Row],[Month_key]]) / SUMIFS(Expense_master[Days_in_Month],Expense_master[Month_Key],Daily_Data[[#This Row],[Month_key]])) + Daily_Data[[#This Row],[Rooms_Occupied]] * ( (0.6 * SUMIFS(Expense_master[Electicity_Bill],Expense_master[Month_Key], Daily_Data[[#This Row],[Month_key]])) / SUMIFS(Occupancy_table[Monthly_rooms_Occupied],Occupancy_table[Month_Key],Daily_Data[[#This Row],[Month_key]])) -> 1740.2844 | O24: =SUMIFS(Expense_master[Monthly_Maintenance],Expense_master[Month_Key],Daily_Data[[#This Row],[Month_key]]) / SUMIFS(Expense_master[Days_in_Month],Expense_master[Month_Key], Daily_Data[[#This Row],[Month_key]]) -> 645.16129 | P24: =Daily_Data[[#This Row],[OTA Commision]] + Daily_Data[[#This Row],[Daily_Rent]]+Daily_Data[[#This Row],[Daily_Staff]]+Daily_Data[[#This Row],[Daily_HK]]+Daily_Data[[#This Row],[Daily_Electricity]] + Daily_Data[[#This Row],[Daily Maintenance]] -> 15234.058 | Q24: =Daily_Data[[#This Row],[Total_Sales]]-Daily_Data[[#This Row],[Total_Daily_Expense]] -> 3521.942 | R24: =Daily_Data[[#This Row],[Total_Sales]]/Daily_Data[[#This Row],[Rooms_Occupied]] -> 1563 | S24: =Daily_Data[[#This Row],[Total_Sales]] / Daily_Data[[#This Row],[Max_rooms]] -> 1339.7143
A25: 44950 | B25: =DATE(YEAR(Daily_Data[[#This Row],[Date]]), MONTH(Daily_Data[[#This Row],[Date]]), 1) -> 44927 | C25: =TEXT(Daily_Data[[#This Row],[Month_key]],"mmmm") -> January | D25: =TEXT(Daily_Data[[#This Row],[Month_key]],"yyyy") -> 2023 | E25: 12 | F25: 14 | G25: =Daily_Data[[#This Row],[Rooms_Occupied]]/F25 -> 0.85714286 | H25: 1949 | I25: =Daily_Data[[#This Row],[Room_rate]]*Daily_Data[[#This Row],[Rooms_Occupied]] -> 23388 | J25: =Daily_Data[[#This Row],[Total_Sales]] * 0.22 -> 5145.36 | K25: =INDEX(Expense_master[Monthly_Rent],MATCH(Daily_Data[[#This Row],[Month_key]],Expense_master[Month_Key],0)) / INDEX(Expense_master[Days_in_Month],MATCH(Daily_Data[[#This Row],[Month_key]],Expense_master[Month_Key],0)) -> 6129.0323 | L25: =SUMIFS(Expense_master[Staff_Salary],Expense_master[Month_Key],Daily_Data[[#This Row],[Month_key]]) / SUMIFS(Expense_master[Days_in_Month],Expense_master[Month_Key],Daily_Data[[#This Row],[Month_key]]) -> 2258.0645 | M25: =Daily_Data[[#This Row],[Rooms_Occupied]] * (SUMIFS(Expense_master[Housekeeping_Laundy],Expense_master[Month_Key],Daily_Data[[#This Row],[Month_key]]) / SUMIFS(Occupancy_table[Monthly_rooms_Occupied],Occupancy_table[Month_Key],Daily_Data[[#This Row],[Month_key]])) -> 335.19553 | N25: =0.4 * (SUMIFS(Expense_master[Electicity_Bill],Expense_master[Month_Key],Daily_Data[[#This Row],[Month_key]]) / SUMIFS(Expense_master[Days_in_Month],Expense_master[Month_Key],Daily_Data[[#This Row],[Month_key]])) + Daily_Data[[#This Row],[Rooms_Occupied]] * ( (0.6 * SUMIFS(Expense_master[Electicity_Bill],Expense_master[Month_Key], Daily_Data[[#This Row],[Month_key]])) / SUMIFS(Occupancy_table[Monthly_rooms_Occupied],Occupancy_table[Month_Key],Daily_Data[[#This Row],[Month_key]])) -> 1740.2844 | O25: =SUMIFS(Expense_master[Monthly_Maintenance],Expense_master[Month_Key],Daily_Data[[#This Row],[Month_key]]) / SUMIFS(Expense_master[Days_in_Month],Expense_master[Month_Key], Daily_Data[[#This Row],[Month_key]]) -> 645.16129 | P25: =Daily_Data[[#This Row],[OTA Commision]] + Daily_Data[[#This Row],[Daily_Rent]]+Daily_Data[[#This Row],[Daily_Staff]]+Daily_Data[[#This Row],[Daily_HK]]+Daily_Data[[#This Row],[Daily_Electricity]] + Daily_Data[[#This Row],[Daily Maintenance]] -> 16253.098 | Q25: =Daily_Data[[#This Row],[Total_Sales]]-Daily_Data[[#This Row],[Total_Daily_Expense]] -> 7134.902 | R25: =Daily_Data[[#This Row],[Total_Sales]]/Daily_Data[[#This Row],[Rooms_Occupied]] -> 1949 | S25: =Daily_Data[[#This Row],[Total_Sales]] / Daily_Data[[#This Row],[Max_rooms]] -> 1670.5714
A26: 44951 | B26: =DATE(YEAR(Daily_Data[[#This Row],[Date]]), MONTH(Daily_Data[[#This Row],[Date]]), 1) -> 44927 | C26: =TEXT(Daily_Data[[#This Row],[Month_key]],"mmmm") -> January | D26: =TEXT(Daily_Data[[#This Row],[Month_key]],"yyyy") -> 2023 | E26: 9 | F26: 14 | G26: =Daily_Data[[#This Row],[Rooms_Occupied]]/F26 -> 0.64285714 | H26: 1231 | I26: =Daily_Data[[#This Row],[Room_rate]]*Daily_Data[[#This Row],[Rooms_Occupied]] -> 11079 | J26: =Daily_Data[[#This Row],[Total_Sales]] * 0.22 -> 2437.38 | K26: =INDEX(Expense_master[Monthly_Rent],MATCH(Daily_Data[[#This Row],[Month_key]],Expense_master[Month_Key],0)) / INDEX(Expense_master[Days_in_Month],MATCH(Daily_Data[[#This Row],[Month_key]],Expense_master[Month_Key],0)) -> 6129.0323 | L26: =SUMIFS(Expense_master[Staff_Salary],Expense_master[Month_Key],Daily_Data[[#This Row],[Month_key]]) / SUMIFS(Expense_master[Days_in_Month],Expense_master[Month_Key],Daily_Data[[#This Row],[Month_key]]) -> 2258.0645 | M26: =Daily_Data[[#This Row],[Rooms_Occupied]] * (SUMIFS(Expense_master[Housekeeping_Laundy],Expense_master[Month_Key],Daily_Data[[#This Row],[Month_key]]) / SUMIFS(Occupancy_table[Monthly_rooms_Occupied],Occupancy_table[Month_Key],Daily_Data[[#This Row],[Month_key]])) -> 251.39665 | N26: =0.4 * (SUMIFS(Expense_master[Electicity_Bill],Expense_master[Month_Key],Daily_Data[[#This Row],[Month_key]]) / SUMIFS(Expense_master[Days_in_Month],Expense_master[Month_Key],Daily_Data[[#This Row],[Month_key]])) + Daily_Data[[#This Row],[Rooms_Occupied]] * ( (0.6 * SUMIFS(Expense_master[Electicity_Bill],Expense_master[Month_Key], Daily_Data[[#This Row],[Month_key]])) / SUMIFS(Occupancy_table[Monthly_rooms_Occupied],Occupancy_table[Month_Key],Daily_Data[[#This Row],[Month_key]])) -> 1475.252 | O26: =SUMIFS(Expense_master[Monthly_Maintenance],Expense_master[Month_Key],Daily_Data[[#This Row],[Month_key]]) / SUMIFS(Expense_master[Days_in_Month],Expense_master[Month_Key], Daily_Data[[#This Row],[Month_key]]) -> 645.16129 | P26: =Daily_Data[[#This Row],[OTA Commision]] + Daily_Data[[#This Row],[Daily_Rent]]+Daily_Data[[#This Row],[Daily_Staff]]+Daily_Data[[#This Row],[Daily_HK]]+Daily_Data[[#This Row],[Daily_Electricity]] + Daily_Data[[#This Row],[Daily Maintenance]] -> 13196.287 | Q26: =Daily_Data[[#This Row],[Total_Sales]]-Daily_Data[[#This Row],[Total_Daily_Expense]] -> -2117.2868 | R26: =Daily_Data[[#This Row],[Total_Sales]]/Daily_Data[[#This Row],[Rooms_Occupied]] -> 1231 | S26: =Daily_Data[[#This Row],[Total_Sales]] / Daily_Data[[#This Row],[Max_rooms]] -> 791.35714
A27: 44952 | B27: =DATE(YEAR(Daily_Data[[#This Row],[Date]]), MONTH(Daily_Data[[#This Row],[Date]]), 1) -> 44927 | C27: =TEXT(Daily_Data[[#This Row],[Month_key]],"mmmm") -> January | D27: =TEXT(Daily_Data[[#This Row],[Month_key]],"yyyy") -> 2023 | E27: 14 | F27: 14 | G27: =Daily_Data[[#This Row],[Rooms_Occupied]]/F27 -> 1 | H27: 1917 | I27: =Daily_Data[[#This Row],[Room_rate]]*Daily_Data[[#This Row],[Rooms_Occupied]] -> 26838 | J27: =Daily_Data[[#This Row],[Total_Sales]] * 0.22 -> 5904.36 | K27: =INDEX(Expense_master[Monthly_Rent],MATCH(Daily_Data[[#This Row],[Month_key]],Expense_master[Month_Key],0)) / INDEX(Expense_master[Days_in_Month],MATCH(Daily_Data[[#This Row],[Month_key]],Expense_master[Month_Key],0)) -> 6129.0323 | L27: =SUMIFS(Expense_master[Staff_Salary],Expense_master[Month_Key],Daily_Data[[#This Row],[Month_key]]) / SUMIFS(Expense_master[Days_in_Month],Expense_master[Month_Key],Daily_Data[[#This Row],[Month_key]]) -> 2258.0645 | M27: =Daily_Data[[#This Row],[Rooms_Occupied]] * (SUMIFS(Expense_master[Housekeeping_Laundy],Expense_master[Month_Key],Daily_Data[[#This Row],[Month_key]]) / SUMIFS(Occupancy_table[Monthly_rooms_Occupied],Occupancy_table[Month_Key],Daily_Data[[#This Row],[Month_key]])) -> 391.06145 | N27: =0.4 * (SUMIFS(Expense_master[Electicity_Bill],Expense_master[Month_Key],Daily_Data[[#This Row],[Month_key]]) / SUMIFS(Expense_master[Days_in_Month],Expense_master[Month_Key],Daily_Data[[#This Row],[Month_key]])) + Daily_Data[[#This Row],[Rooms_Occupied]] * ( (0.6 * SUMIFS(Expense_master[Electicity_Bill],Expense_master[Month_Key], Daily_Data[[#This Row],[Month_key]])) / SUMIFS(Occupancy_table[Monthly_rooms_Occupied],Occupancy_table[Month_Key],Daily_Data[[#This Row],[Month_key]])) -> 1916.9727 | O27: =SUMIFS(Expense_master[Monthly_Maintenance],Expense_master[Month_Key],Daily_Data[[#This Row],[Month_key]]) / SUMIFS(Expense_master[Days_in_Month],Expense_master[Month_Key], Daily_Data[[#This Row],[Month_key]]) -> 645.16129 | P27: =Daily_Data[[#This Row],[OTA Commision]] + Daily_Data[[#This Row],[Daily_Rent]]+Daily_Data[[#This Row],[Daily_Staff]]+Daily_Data[[#This Row],[Daily_HK]]+Daily_Data[[#This Row],[Daily_Electricity]] + Daily_Data[[#This Row],[Daily Maintenance]] -> 17244.652 | Q27: =Daily_Data[[#This Row],[Total_Sales]]-Daily_Data[[#This Row],[Total_Daily_Expense]] -> 9593.3478 | R27: =Daily_Data[[#This Row],[Total_Sales]]/Daily_Data[[#This Row],[Rooms_Occupied]] -> 1917 | S27: =Daily_Data[[#This Row],[Total_Sales]] / Daily_Data[[#This Row],[Max_rooms]] -> 1917
A28: 44953 | B28: =DATE(YEAR(Daily_Data[[#This Row],[Date]]), MONTH(Daily_Data[[#This Row],[Date]]), 1) -> 44927 | C28: =TEXT(Daily_Data[[#This Row],[Month_key]],"mmmm") -> January | D28: =TEXT(Daily_Data[[#This Row],[Month_key]],"yyyy") -> 2023 | E28: 11 | F28: 14 | G28: =Daily_Data[[#This Row],[Rooms_Occupied]]/F28 -> 0.78571429 | H28: 1910 | I28: =Daily_Data[[#This Row],[Room_rate]]*Daily_Data[[#This Row],[Rooms_Occupied]] -> 21010 | J28: =Daily_Data[[#This Row],[Total_Sales]] * 0.22 -> 4622.2 | K28: =INDEX(Expense_master[Monthly_Rent],MATCH(Daily_Data[[#This Row],[Month_key]],Expense_master[Month_Key],0)) / INDEX(Expense_master[Days_in_Month],MATCH(Daily_Data[[#This Row],[Month_key]],Expense_master[Month_Key],0)) -> 6129.0323 | L28: =SUMIFS(Expense_master[Staff_Salary],Expense_master[Month_Key],Daily_Data[[#This Row],[Month_key]]) / SUMIFS(Expense_master[Days_in_Month],Expense_master[Month_Key],Daily_Data[[#This Row],[Month_key]]) -> 2258.0645 | M28: =Daily_Data[[#This Row],[Rooms_Occupied]] * (SUMIFS(Expense_master[Housekeeping_Laundy],Expense_master[Month_Key],Daily_Data[[#This Row],[Month_key]]) / SUMIFS(Occupancy_table[Monthly_rooms_Occupied],Occupancy_table[Month_Key],Daily_Data[[#This Row],[Month_key]])) -> 307.26257 | N28: =0.4 * (SUMIFS(Expense_master[Electicity_Bill],Expense_master[Month_Key],Daily_Data[[#This Row],[Month_key]]) / SUMIFS(Expense_master[Days_in_Month],Expense_master[Month_Key],Daily_Data[[#This Row],[Month_key]])) + Daily_Data[[#This Row],[Rooms_Occupied]] * ( (0.6 * SUMIFS(Expense_master[Electicity_Bill],Expense_master[Month_Key], Daily_Data[[#This Row],[Month_key]])) / SUMIFS(Occupancy_table[Monthly_rooms_Occupied],Occupancy_table[Month_Key],Daily_Data[[#This Row],[Month_key]])) -> 1651.9403 | O28: =SUMIFS(Expense_master[Monthly_Maintenance],Expense_master[Month_Key],Daily_Data[[#This Row],[Month_key]]) / SUMIFS(Expense_master[Days_in_Month],Expense_master[Month_Key], Daily_Data[[#This Row],[Month_key]]) -> 645.16129 | P28: =Daily_Data[[#This Row],[OTA Commision]] + Daily_Data[[#This Row],[Daily_Rent]]+Daily_Data[[#This Row],[Daily_Staff]]+Daily_Data[[#This Row],[Daily_HK]]+Daily_Data[[#This Row],[Daily_Electricity]] + Daily_Data[[#This Row],[Daily Maintenance]] -> 15613.661 | Q28: =Daily_Data[[#This Row],[Total_Sales]]-Daily_Data[[#This Row],[Total_Daily_Expense]] -> 5396.3391 | R28: =Daily_Data[[#This Row],[Total_Sales]]/Daily_Data[[#This Row],[Rooms_Occupied]] -> 1910 | S28: =Daily_Data[[#This Row],[Total_Sales]] / Daily_Data[[#This Row],[Max_rooms]] -> 1500.7143
A29: 44954 | B29: =DATE(YEAR(Daily_Data[[#This Row],[Date]]), MONTH(Daily_Data[[#This Row],[Date]]), 1) -> 44927 | C29: =TEXT(Daily_Data[[#This Row],[Month_key]],"mmmm") -> January | D29: =TEXT(Daily_Data[[#This Row],[Month_key]],"yyyy") -> 2023 | E29: 14 | F29: 14 | G29: =Daily_Data[[#This Row],[Rooms_Occupied]]/F29 -> 1 | H29: 1776 | I29: =Daily_Data[[#This Row],[Room_rate]]*Daily_Data[[#This Row],[Rooms_Occupied]] -> 24864 | J29: =Daily_Data[[#This Row],[Total_Sales]] * 0.22 -> 5470.08 | K29: =INDEX(Expense_master[Monthly_Rent],MATCH(Daily_Data[[#This Row],[Month_key]],Expense_master[Month_Key],0)) / INDEX(Expense_master[Days_in_Month],MATCH(Daily_Data[[#This Row],[Month_key]],Expense_master[Month_Key],0)) -> 6129.0323 | L29: =SUMIFS(Expense_master[Staff_Salary],Expense_master[Month_Key],Daily_Data[[#This Row],[Month_key]]) / SUMIFS(Expense_master[Days_in_Month],Expense_master[Month_Key],Daily_Data[[#This Row],[Month_key]]) -> 2258.0645 | M29: =Daily_Data[[#This Row],[Rooms_Occupied]] * (SUMIFS(Expense_master[Housekeeping_Laundy],Expense_master[Month_Key],Daily_Data[[#This Row],[Month_key]]) / SUMIFS(Occupancy_table[Monthly_rooms_Occupied],Occupancy_table[Month_Key],Daily_Data[[#This Row],[Month_key]])) -> 391.06145 | N29: =0.4 * (SUMIFS(Expense_master[Electicity_Bill],Expense_master[Month_Key],Daily_Data[[#This Row],[Month_key]]) / SUMIFS(Expense_master[Days_in_Month],Expense_master[Month_Key],Daily_Data[[#This Row],[Month_key]])) + Daily_Data[[#This Row],[Rooms_Occupied]] * ( (0.6 * SUMIFS(Expense_master[Electicity_Bill],Expense_master[Month_Key], Daily_Data[[#This Row],[Month_key]])) / SUMIFS(Occupancy_table[Monthly_rooms_Occupied],Occupancy_table[Month_Key],Daily_Data[[#This Row],[Month_key]])) -> 1916.9727 | O29: =SUMIFS(Expense_master[Monthly_Maintenance],Expense_master[Month_Key],Daily_Data[[#This Row],[Month_key]]) / SUMIFS(Expense_master[Days_in_Month],Expense_master[Month_Key], Daily_Data[[#This Row],[Month_key]]) -> 645.16129 | P29: =Daily_Data[[#This Row],[OTA Commision]] + Daily_Data[[#This Row],[Daily_Rent]]+Daily_Data[[#This Row],[Daily_Staff]]+Daily_Data[[#This Row],[Daily_HK]]+Daily_Data[[#This Row],[Daily_Electricity]] + Daily_Data[[#This Row],[Daily Maintenance]] -> 16810.372 | Q29: =Daily_Data[[#This Row],[Total_Sales]]-Daily_Data[[#This Row],[Total_Daily_Expense]] -> 8053.6278 | R29: =Daily_Data[[#This Row],[Total_Sales]]/Daily_Data[[#This Row],[Rooms_Occupied]] -> 1776 | S29: =Daily_Data[[#This Row],[Total_Sales]] / Daily_Data[[#This Row],[Max_rooms]] -> 1776
A30: 44955 | B30: =DATE(YEAR(Daily_Data[[#This Row],[Date]]), MONTH(Daily_Data[[#This Row],[Date]]), 1) -> 44927 | C30: =TEXT(Daily_Data[[#This Row],[Month_key]],"mmmm") -> January | D30: =TEXT(Daily_Data[[#This Row],[Month_key]],"yyyy") -> 2023 | E30: 11 | F30: 14 | G30: =Daily_Data[[#This Row],[Rooms_Occupied]]/F30 -> 0.78571429 | H30: 1547 | I30: =Daily_Data[[#This Row],[Room_rate]]*Daily_Data[[#This Row],[Rooms_Occupied]] -> 17017 | J30: =Daily_Data[[#This Row],[Total_Sales]] * 0.22 -> 3743.74 | K30: =INDEX(Expense_master[Monthly_Rent],MATCH(Daily_Data[[#This Row],[Month_key]],Expense_master[Month_Key],0)) / INDEX(Expense_master[Days_in_Month],MATCH(Daily_Data[[#This Row],[Month_key]],Expense_master[Month_Key],0)) -> 6129.0323 | L30: =SUMIFS(Expense_master[Staff_Salary],Expense_master[Month_Key],Daily_Data[[#This Row],[Month_key]]) / SUMIFS(Expense_master[Days_in_Month],Expense_master[Month_Key],Daily_Data[[#This Row],[Month_key]]) -> 2258.0645 | M30: =Daily_Data[[#This Row],[Rooms_Occupied]] * (SUMIFS(Expense_master[Housekeeping_Laundy],Expense_master[Month_Key],Daily_Data[[#This Row],[Month_key]]) / SUMIFS(Occupancy_table[Monthly_rooms_Occupied],Occupancy_table[Month_Key],Daily_Data[[#This Row],[Month_key]])) -> 307.26257 | N30: =0.4 * (SUMIFS(Expense_master[Electicity_Bill],Expense_master[Month_Key],Daily_Data[[#This Row],[Month_key]]) / SUMIFS(Expense_master[Days_in_Month],Expense_master[Month_Key],Daily_Data[[#This Row],[Month_key]])) + Daily_Data[[#This Row],[Rooms_Occupied]] * ( (0.6 * SUMIFS(Expense_master[Electicity_Bill],Expense_master[Month_Key], Daily_Data[[#This Row],[Month_key]])) / SUMIFS(Occupancy_table[Monthly_rooms_Occupied],Occupancy_table[Month_Key],Daily_Data[[#This Row],[Month_key]])) -> 1651.9403 | O30: =SUMIFS(Expense_master[Monthly_Maintenance],Expense_master[Month_Key],Daily_Data[[#This Row],[Month_key]]) / SUMIFS(Expense_master[Days_in_Month],Expense_master[Month_Key], Daily_Data[[#This Row],[Month_key]]) -> 645.16129 | P30: =Daily_Data[[#This Row],[OTA Commision]] + Daily_Data[[#This Row],[Daily_Rent]]+Daily_Data[[#This Row],[Daily_Staff]]+Daily_Data[[#This Row],[Daily_HK]]+Daily_Data[[#This Row],[Daily_Electricity]] + Daily_Data[[#This Row],[Daily Maintenance]] -> 14735.201 | Q30: =Daily_Data[[#This Row],[Total_Sales]]-Daily_Data[[#This Row],[Total_Daily_Expense]] -> 2281.7991 | R30: =Daily_Data[[#This Row],[Total_Sales]]/Daily_Data[[#This Row],[Rooms_Occupied]] -> 1547 | S30: =Daily_Data[[#This Row],[Total_Sales]] / Daily_Data[[#This Row],[Max_rooms]] -> 1215.5
A31: 44956 | B31: =DATE(YEAR(Daily_Data[[#This Row],[Date]]), MONTH(Daily_Data[[#This Row],[Date]]), 1) -> 44927 | C31: =TEXT(Daily_Data[[#This Row],[Month_key]],"mmmm") -> January | D31: =TEXT(Daily_Data[[#This Row],[Month_key]],"yyyy") -> 2023 | E31: 9 | F31: 14 | G31: =Daily_Data[[#This Row],[Rooms_Occupied]]/F31 -> 0.64285714 | H31: 1864 | I31: =Daily_Data[[#This Row],[Room_rate]]*Daily_Data[[#This Row],[Rooms_Occupied]] -> 16776 | J31: =Daily_Data[[#This Row],[Total_Sales]] * 0.22 -> 3690.72 | K31: =INDEX(Expense_master[Monthly_Rent],MATCH(Daily_Data[[#This Row],[Month_key]],Expense_master[Month_Key],0)) / INDEX(Expense_master[Days_in_Month],MATCH(Daily_Data[[#This Row],[Month_key]],Expense_master[Month_Key],0)) -> 6129.0323 | L31: =SUMIFS(Expense_master[Staff_Salary],Expense_master[Month_Key],Daily_Data[[#This Row],[Month_key]]) / SUMIFS(Expense_master[Days_in_Month],Expense_master[Month_Key],Daily_Data[[#This Row],[Month_key]]) -> 2258.0645 | M31: =Daily_Data[[#This Row],[Rooms_Occupied]] * (SUMIFS(Expense_master[Housekeeping_Laundy],Expense_master[Month_Key],Daily_Data[[#This Row],[Month_key]]) / SUMIFS(Occupancy_table[Monthly_rooms_Occupied],Occupancy_table[Month_Key],Daily_Data[[#This Row],[Month_key]])) -> 251.39665 | N31: =0.4 * (SUMIFS(Expense_master[Electicity_Bill],Expense_master[Month_Key],Daily_Data[[#This Row],[Month_key]]) / SUMIFS(Expense_master[Days_in_Month],Expense_master[Month_Key],Daily_Data[[#This Row],[Month_key]])) + Daily_Data[[#This Row],[Rooms_Occupied]] * ( (0.6 * SUMIFS(Expense_master[Electicity_Bill],Expense_master[Month_Key], Daily_Data[[#This Row],[Month_key]])) / SUMIFS(Occupancy_table[Monthly_rooms_Occupied],Occupancy_table[Month_Key],Daily_Data[[#This Row],[Month_key]])) -> 1475.252 | O31: =SUMIFS(Expense_master[Monthly_Maintenance],Expense_master[Month_Key],Daily_Data[[#This Row],[Month_key]]) / SUMIFS(Expense_master[Days_in_Month],Expense_master[Month_Key], Daily_Data[[#This Row],[Month_key]]) -> 645.16129 | P31: =Daily_Data[[#This Row],[OTA Commision]] + Daily_Data[[#This Row],[Daily_Rent]]+Daily_Data[[#This Row],[Daily_Staff]]+Daily_Data[[#This Row],[Daily_HK]]+Daily_Data[[#This Row],[Daily_Electricity]] + Daily_Data[[#This Row],[Daily Maintenance]] -> 14449.627 | Q31: =Daily_Data[[#This Row],[Total_Sales]]-Daily_Data[[#This Row],[Total_Daily_Expense]] -> 2326.3732 | R31: =Daily_Data[[#This Row],[Total_Sales]]/Daily_Data[[#This Row],[Rooms_Occupied]] -> 1864 | S31: =Daily_Data[[#This Row],[Total_Sales]] / Daily_Data[[#This Row],[Max_rooms]] -> 1198.2857
A32: 44957 | B32: =DATE(YEAR(Daily_Data[[#This Row],[Date]]), MONTH(Daily_Data[[#This Row],[Date]]), 1) -> 44927 | C32: =TEXT(Daily_Data[[#This Row],[Month_key]],"mmmm") -> January | D32: =TEXT(Daily_Data[[#This Row],[Month_key]],"yyyy") -> 2023 | E32: 12 | F32: 14 | G32: =Daily_Data[[#This Row],[Rooms_Occupied]]/F32 -> 0.85714286 | H32: 1937 | I32: =Daily_Data[[#This Row],[Room_rate]]*Daily_Data[[#This Row],[Rooms_Occupied]] -> 23244 | J32: =Daily_Data[[#This Row],[Total_Sales]] * 0.22 -> 5113.68 | K32: =INDEX(Expense_master[Monthly_Rent],MATCH(Daily_Data[[#This Row],[Month_key]],Expense_master[Month_Key],0)) / INDEX(Expense_master[Days_in_Month],MATCH(Daily_Data[[#This Row],[Month_key]],Expense_master[Month_Key],0)) -> 6129.0323 | L32: =SUMIFS(Expense_master[Staff_Salary],Expense_master[Month_Key],Daily_Data[[#This Row],[Month_key]]) / SUMIFS(Expense_master[Days_in_Month],Expense_master[Month_Key],Daily_Data[[#This Row],[Month_key]]) -> 2258.0645 | M32: =Daily_Data[[#This Row],[Rooms_Occupied]] * (SUMIFS(Expense_master[Housekeeping_Laundy],Expense_master[Month_Key],Daily_Data[[#This Row],[Month_key]]) / SUMIFS(Occupancy_table[Monthly_rooms_Occupied],Occupancy_table[Month_Key],Daily_Data[[#This Row],[Month_key]])) -> 335.19553 | N32: =0.4 * (SUMIFS(Expense_master[Electicity_Bill],Expense_master[Month_Key],Daily_Data[[#This Row],[Month_key]]) / SUMIFS(Expense_master[Days_in_Month],Expense_master[Month_Key],Daily_Data[[#This Row],[Month_key]])) + Daily_Data[[#This Row],[Rooms_Occupied]] * ( (0.6 * SUMIFS(Expense_master[Electicity_Bill],Expense_master[Month_Key], Daily_Data[[#This Row],[Month_key]])) / SUMIFS(Occupancy_table[Monthly_rooms_Occupied],Occupancy_table[Month_Key],Daily_Data[[#This Row],[Month_key]])) -> 1740.2844 | O32: =SUMIFS(Expense_master[Monthly_Maintenance],Expense_master[Month_Key],Daily_Data[[#This Row],[Month_key]]) / SUMIFS(Expense_master[Days_in_Month],Expense_master[Month_Key], Daily_Data[[#This Row],[Month_key]]) -> 645.16129 | P32: =Daily_Data[[#This Row],[OTA Commision]] + Daily_Data[[#This Row],[Daily_Rent]]+Daily_Data[[#This Row],[Daily_Staff]]+Daily_Data[[#This Row],[Daily_HK]]+Daily_Data[[#This Row],[Daily_Electricity]] + Daily_Data[[#This Row],[Daily Maintenance]] -> 16221.418 | Q32: =Daily_Data[[#This Row],[Total_Sales]]-Daily_Data[[#This Row],[Total_Daily_Expense]] -> 7022.582 | R32: =Daily_Data[[#This Row],[Total_Sales]]/Daily_Data[[#This Row],[Rooms_Occupied]] -> 1937 | S32: =Daily_Data[[#This Row],[Total_Sales]] / Daily_Data[[#This Row],[Max_rooms]] -> 1660.2857
... A732: 45657 | B732: =DATE(YEAR(Daily_Data[[#This Row],[Date]]), MONTH(Daily_Data[[#This Row],[Date]]), 1) -> 45627 | C732: =TEXT(Daily_Data[[#This Row],[Month_key]],"mmmm") -> December | D732: =TEXT(Daily_Data[[#This Row],[Month_key]],"yyyy") -> 2024 | E732: 14 | F732: 14 | G732: =Daily_Data[[#This Row],[Rooms_Occupied]]/F732 -> 1 | H732: 1395 | I732: =Daily_Data[[#This Row],[Room_rate]]*Daily_Data[[#This Row],[Rooms_Occupied]] -> 19530 | J732: =Daily_Data[[#This Row],[Total_Sales]] * 0.22 -> 4296.6 | K732: =INDEX(Expense_master[Monthly_Rent],MATCH(Daily_Data[[#This Row],[Month_key]],Expense_master[Month_Key],0)) / INDEX(Expense_master[Days_in_Month],MATCH(Daily_Data[[#This Row],[Month_key]],Expense_master[Month_Key],0)) -> 8064.5161 | L732: =SUMIFS(Expense_master[Staff_Salary],Expense_master[Month_Key],Daily_Data[[#This Row],[Month_key]]) / SUMIFS(Expense_master[Days_in_Month],Expense_master[Month_Key],Daily_Data[[#This Row],[Month_key]]) -> 2258.0645 | M732: =Daily_Data[[#This Row],[Rooms_Occupied]] * (SUMIFS(Expense_master[Housekeeping_Laundy],Expense_master[Month_Key],Daily_Data[[#This Row],[Month_key]]) / SUMIFS(Occupancy_table[Monthly_rooms_Occupied],Occupancy_table[Month_Key],Daily_Data[[#This Row],[Month_key]])) -> 421.68675 | N732: =0.4 * (SUMIFS(Expense_master[Electicity_Bill],Expense_master[Month_Key],Daily_Data[[#This Row],[Month_key]]) / SUMIFS(Expense_master[Days_in_Month],Expense_master[Month_Key],Daily_Data[[#This Row],[Month_key]])) + Daily_Data[[#This Row],[Rooms_Occupied]] * ( (0.6 * SUMIFS(Expense_master[Electicity_Bill],Expense_master[Month_Key], Daily_Data[[#This Row],[Month_key]])) / SUMIFS(Occupancy_table[Monthly_rooms_Occupied],Occupancy_table[Month_Key],Daily_Data[[#This Row],[Month_key]])) -> 1936.468 | O732: =SUMIFS(Expense_master[Monthly_Maintenance],Expense_master[Month_Key],Daily_Data[[#This Row],[Month_key]]) / SUMIFS(Expense_master[Days_in_Month],Expense_master[Month_Key], Daily_Data[[#This Row],[Month_key]]) -> 645.16129 | P732: =Daily_Data[[#This Row],[OTA Commision]] + Daily_Data[[#This Row],[Daily_Rent]]+Daily_Data[[#This Row],[Daily_Staff]]+Daily_Data[[#This Row],[Daily_HK]]+Daily_Data[[#This Row],[Daily_Electricity]] + Daily_Data[[#This Row],[Daily Maintenance]] -> 17622.497 | Q732: =Daily_Data[[#This Row],[Total_Sales]]-Daily_Data[[#This Row],[Total_Daily_Expense]] -> 1907.5033 | R732: =Daily_Data[[#This Row],[Total_Sales]]/Daily_Data[[#This Row],[Rooms_Occupied]] -> 1395 | S732: =Daily_Data[[#This Row],[Total_Sales]] / Daily_Data[[#This Row],[Max_rooms]] -> 1395

Sheet expense_data
A1: Month | B1: Year | C1: Month_Key | D1: Monthly_Rent | E1: Staff_Salary | F1: Housekeeping_Laundy | G1: Electicity_Bill | H1: Monthly_Maintenance | I1: Days_in_Month | J1: OTA_Commission | K1: Total_expense
A2: Jan | B2: 2023 | C2: =DATE(Expense_master[[#This Row],[Year]], MATCH(Expense_master[[#This Row],[Month]],{"Jan","Feb","Mar","Apr","May","Jun","Jul","Aug","Sep","Oct","Nov","Dec"},0), 1) -> 44927 | D2: 190000 | E2: 70000 | F2: 10000 | G2: 52712 | H2: 20000 | I2: 31 | J2: =SUMIFS(Daily_Data[OTA Commision],Daily_Data[Month_key],Expense_master[[#This Row],[Month_Key]]) -> 126379 | K2: =Expense_master[[#This Row],[Monthly_Rent]]+Expense_master[[#This Row],[Staff_Salary]]+Expense_master[[#This Row],[Housekeeping_Laundy]]+Expense_master[[#This Row],[Electicity_Bill]]+Expense_master[[#This Row],[Monthly_Maintenance]]+Expense_master[[#This Row],[OTA_Commission]] -> 469091
A3: Feb | B3: 2023 | C3: =DATE(Expense_master[[#This Row],[Year]], MATCH(Expense_master[[#This Row],[Month]],{"Jan","Feb","Mar","Apr","May","Jun","Jul","Aug","Sep","Oct","Nov","Dec"},0), 1) -> 44958 | D3: 190000 | E3: 70000 | F3: 10000 | G3: 50283 | H3: 20000 | I3: 28 | J3: =SUMIFS(Daily_Data[OTA Commision],Daily_Data[Month_key],Expense_master[[#This Row],[Month_Key]]) -> 104186.28 | K3: =Expense_master[[#This Row],[Monthly_Rent]]+Expense_master[[#This Row],[Staff_Salary]]+Expense_master[[#This Row],[Housekeeping_Laundy]]+Expense_master[[#This Row],[Electicity_Bill]]+Expense_master[[#This Row],[Monthly_Maintenance]]+Expense_master[[#This Row],[OTA_Commission]] -> 444469.28
A4: Mar | B4: 2023 | C4: =DATE(Expense_master[[#This Row],[Year]], MATCH(Expense_master[[#This Row],[Month]],{"Jan","Feb","Mar","Apr","May","Jun","Jul","Aug","Sep","Oct","Nov","Dec"},0), 1) -> 44986 | D4: 190000 | E4: 70000 | F4: 10000 | G4: 48590 | H4: 20000 | I4: 31 | J4: =SUMIFS(Daily_Data[OTA Commision],Daily_Data[Month_key],Expense_master[[#This Row],[Month_Key]]) -> 111347.94 | K4: =Expense_master[[#This Row],[Monthly_Rent]]+Expense_master[[#This Row],[Staff_Salary]]+Expense_master[[#This Row],[Housekeeping_Laundy]]+Expense_master[[#This Row],[Electicity_Bill]]+Expense_master[[#This Row],[Monthly_Maintenance]]+Expense_master[[#This Row],[OTA_Commission]] -> 449937.94
A5: Apr | B5: 2023 | C5: =DATE(Expense_master[[#This Row],[Year]], MATCH(Expense_master[[#This Row],[Month]],{"Jan","Feb","Mar","Apr","May","Jun","Jul","Aug","Sep","Oct","Nov","Dec"},0), 1) -> 45017 | D5: 210000 | E5: 70000 | F5: 10000 | G5: 48930 | H5: 20000 | I5: 30 | J5: =SUMIFS(Daily_Data[OTA Commision],Daily_Data[Month_key],Expense_master[[#This Row],[Month_Key]]) -> 107825.52 | K5: =Expense_master[[#This Row],[Monthly_Rent]]+Expense_master[[#This Row],[Staff_Salary]]+Expense_master[[#This Row],[Housekeeping_Laundy]]+Expense_master[[#This Row],[Electicity_Bill]]+Expense_master[[#This Row],[Monthly_Maintenance]]+Expense_master[[#This Row],[OTA_Commission]] -> 466755.52
A6: May | B6: 2023 | C6: =DATE(Expense_master[[#This Row],[Year]], MATCH(Expense_master[[#This Row],[Month]],{"Jan","Feb","Mar","Apr","May","Jun","Jul","Aug","Sep","Oct","Nov","Dec"},0), 1) -> 45047 | D6: 210000 | E6: 70000 | F6: 10000 | G6: 51290 | H6: 20000 | I6: 31 | J6: =SUMIFS(Daily_Data[OTA Commision],Daily_Data[Month_key],Expense_master[[#This Row],[Month_Key]]) -> 120000.98 | K6: =Expense_master[[#This Row],[Monthly_Rent]]+Expense_master[[#This Row],[Staff_Salary]]+Expense_master[[#This Row],[Housekeeping_Laundy]]+Expense_master[[#This Row],[Electicity_Bill]]+Expense_master[[#This Row],[Monthly_Maintenance]]+Expense_master[[#This Row],[OTA_Commission]] -> 481290.98
A7: Jun | B7: 2023 | C7: =DATE(Expense_master[[#This Row],[Year]], MATCH(Expense_master[[#This Row],[Month]],{"Jan","Feb","Mar","Apr","May","Jun","Jul","Aug","Sep","Oct","Nov","Dec"},0), 1) -> 45078 | D7: 210000 | E7: 70000 | F7: 10000 | G7: 48418 | H7: 20000 | I7: 30 | J7: =SUMIFS(Daily_Data[OTA Commision],Daily_Data[Month_key],Expense_master[[#This Row],[Month_Key]]) -> 108739.84 | K7: =Expense_master[[#This Row],[Monthly_Rent]]+Expense_master[[#This Row],[Staff_Salary]]+Expense_master[[#This Row],[Housekeeping_Laundy]]+Expense_master[[#This Row],[Electicity_Bill]]+Expense_master[[#This Row],[Monthly_Maintenance]]+Expense_master[[#This Row],[OTA_Commission]] -> 467157.84
A8: Jul | B8: 2023 | C8: =DATE(Expense_master[[#This Row],[Year]], MATCH(Expense_master[[#This Row],[Month]],{"Jan","Feb","Mar","Apr","May","Jun","Jul","Aug","Sep","Oct","Nov","Dec"},0), 1) -> 45108 | D8: 210000 | E8: 70000 | F8: 10000 | G8: 51567 | H8: 20000 | I8: 31 | J8: =SUMIFS(Daily_Data[OTA Commision],Daily_Data[Month_key],Expense_master[[#This Row],[Month_Key]]) -> 116433.9 | K8: =Expense_master[[#This Row],[Monthly_Rent]]+Expense_master[[#This Row],[Staff_Salary]]+Expense_master[[#This Row],[Housekeeping_Laundy]]+Expense_master[[#This Row],[Electicity_Bill]]+Expense_master[[#This Row],[Monthly_Maintenance]]+Expense_master[[#This Row],[OTA_Commission]] -> 478000.9
A9: Aug | B9: 2023 | C9: =DATE(Expense_master[[#This Row],[Year]], MATCH(Expense_master[[#This Row],[Month]],{"Jan","Feb","Mar","Apr","May","Jun","Jul","Aug","Sep","Oct","Nov","Dec"},0), 1) -> 45139 | D9: 210000 | E9: 70000 | F9: 10000 | G9: 50879 | H9: 20000 | I9: 31 | J9: =SUMIFS(Daily_Data[OTA Commision],Daily_Data[Month_key],Expense_master[[#This Row],[Month_Key]]) -> 107848.62 | K9: =Expense_master[[#This Row],[Monthly_Rent]]+Expense_master[[#This Row],[Staff_Salary]]+Expense_master[[#This Row],[Housekeeping_Laundy]]+Expense_master[[#This Row],[Electicity_Bill]]+Expense_master[[#This Row],[Monthly_Maintenance]]+Expense_master[[#This Row],[OTA_Commission]] -> 468727.62
A10: Sep | B10: 2023 | C10: =DATE(Expense_master[[#This Row],[Year]], MATCH(Expense_master[[#This Row],[Month]],{"Jan","Feb","Mar","Apr","May","Jun","Jul","Aug","Sep","Oct","Nov","Dec"},0), 1) -> 45170 | D10: 210000 | E10: 70000 | F10: 10000 | G10: 53333 | H10: 20000 | I10: 30 | J10: =SUMIFS(Daily_Data[OTA Commision],Daily_Data[Month_key],Expense_master[[#This Row],[Month_Key]]) -> 109157.18 | K10: =Expense_master[[#This Row],[Monthly_Rent]]+Expense_master[[#This Row],[Staff_Salary]]+Expense_master[[#This Row],[Housekeeping_Laundy]]+Expense_master[[#This Row],[Electicity_Bill]]+Expense_master[[#This Row],[Monthly_Maintenance]]+Expense_master[[#This Row],[OTA_Commission]] -> 472490.18
A11: Oct | B11: 2023 | C11: =DATE(Expense_master[[#This Row],[Year]], MATCH(Expense_master[[#This Row],[Month]],{"Jan","Feb","Mar","Apr","May","Jun","Jul","Aug","Sep","Oct","Nov","Dec"},0), 1) -> 45200 | D11: 210000 | E11: 70000 | F11: 10000 | G11: 51849 | H11: 20000 | I11: 31 | J11: =SUMIFS(Daily_Data[OTA Commision],Daily_Data[Month_key],Expense_master[[#This Row],[Month_Key]]) -> 113283.5 | K11: =Expense_master[[#This Row],[Monthly_Rent]]+Expense_master[[#This Row],[Staff_Salary]]+Expense_master[[#This Row],[Housekeeping_Laundy]]+Expense_master[[#This Row],[Electicity_Bill]]+Expense_master[[#This Row],[Monthly_Maintenance]]+Expense_master[[#This Row],[OTA_Commission]] -> 475132.5
A12: Nov | B12: 2023 | C12: =DATE(Expense_master[[#This Row],[Year]], MATCH(Expense_master[[#This Row],[Month]],{"Jan","Feb","Mar","Apr","May","Jun","Jul","Aug","Sep","Oct","Nov","Dec"},0), 1) -> 45231 | D12: 210000 | E12: 70000 | F12: 10000 | G12: 52319 | H12: 20000 | I12: 30 | J12: =SUMIFS(Daily_Data[OTA Commision],Daily_Data[Month_key],Expense_master[[#This Row],[Month_Key]]) -> 110210.98 | K12: =Expense_master[[#This Row],[Monthly_Rent]]+Expense_master[[#This Row],[Staff_Salary]]+Expense_master[[#This Row],[Housekeeping_Laundy]]+Expense_master[[#This Row],[Electicity_Bill]]+Expense_master[[#This Row],[Monthly_Maintenance]]+Expense_master[[#This Row],[OTA_Commission]] -> 472529.98
A13: Dec | B13: 2023 | C13: =DATE(Expense_master[[#This Row],[Year]], MATCH(Expense_master[[#This Row],[Month]],{"Jan","Feb","Mar","Apr","May","Jun","Jul","Aug","Sep","Oct","Nov","Dec"},0), 1) -> 45261 | D13: 210000 | E13: 70000 | F13: 10000 | G13: 49939 | H13: 20000 | I13: 31 | J13: =SUMIFS(Daily_Data[OTA Commision],Daily_Data[Month_key],Expense_master[[#This Row],[Month_Key]]) -> 109401.38 | K13: =Expense_master[[#This Row],[Monthly_Rent]]+Expense_master[[#This Row],[Staff_Salary]]+Expense_master[[#This Row],[Housekeeping_Laundy]]+Expense_master[[#This Row],[Electicity_Bill]]+Expense_master[[#This Row],[Monthly_Maintenance]]+Expense_master[[#This Row],[OTA_Commission]] -> 469340.38
... A25: Dec | B25: 2024 | C25: =DATE(Expense_master[[#This Row],[Year]], MATCH(Expense_master[[#This Row],[Month]],{"Jan","Feb","Mar","Apr","May","Jun","Jul","Aug","Sep","Oct","Nov","Dec"},0), 1) -> 45627 | D25: 250000 | E25: 70000 | F25: 10000 | G25: 50687 | H25: 20000 | I25: 31 | J25: =SUMIFS(Daily_Data[OTA Commision],Daily_Data[Month_key],Expense_master[[#This Row],[Month_Key]]) -> 107587.92 | K25: =Expense_master[[#This Row],[Monthly_Rent]]+Expense_master[[#This Row],[Staff_Salary]]+Expense_master[[#This Row],[Housekeeping_Laundy]]+Expense_master[[#This Row],[Electicity_Bill]]+Expense_master[[#This Row],[Monthly_Maintenance]]+Expense_master[[#This Row],[OTA_Commission]] -> 508274.92

Sheet occupancy_data
A1: Month | B1: Year | C1: Month_Key | D1: Monthly_rooms_Occupied
A2: Jan | B2: 2023 | C2: =DATE(Occupancy_table[[#This Row],[Year]], MATCH(Occupancy_table[[#This Row],[Month]],{"Jan","Feb","Mar","Apr","May","Jun","Jul","Aug","Sep","Oct","Nov","Dec"},0),1) -> 44927 | D2: =SUMIFS(Daily_Data[[#All],[Rooms_Occupied]],Daily_Data[[#All],[Month_key]],Occupancy_table[[#All],[Month_Key]]) -> 358
A3: Feb | B3: 2023 | C3: =DATE(Occupancy_table[[#This Row],[Year]], MATCH(Occupancy_table[[#This Row],[Month]],{"Jan","Feb","Mar","Apr","May","Jun","Jul","Aug","Sep","Oct","Nov","Dec"},0),1) -> 44958 | D3: =SUMIFS(Daily_Data[[#All],[Rooms_Occupied]],Daily_Data[[#All],[Month_key]],Occupancy_table[[#All],[Month_Key]]) -> 316
A4: Mar | B4: 2023 | C4: =DATE(Occupancy_table[[#This Row],[Year]], MATCH(Occupancy_table[[#This Row],[Month]],{"Jan","Feb","Mar","Apr","May","Jun","Jul","Aug","Sep","Oct","Nov","Dec"},0),1) -> 44986 | D4: =SUMIFS(Daily_Data[[#All],[Rooms_Occupied]],Daily_Data[[#All],[Month_key]],Occupancy_table[[#All],[Month_Key]]) -> 342
A5: Apr | B5: 2023 | C5: =DATE(Occupancy_table[[#This Row],[Year]], MATCH(Occupancy_table[[#This Row],[Month]],{"Jan","Feb","Mar","Apr","May","Jun","Jul","Aug","Sep","Oct","Nov","Dec"},0),1) -> 45017 | D5: =SUMIFS(Daily_Data[[#All],[Rooms_Occupied]],Daily_Data[[#All],[Month_key]],Occupancy_table[[#All],[Month_Key]]) -> 321
A6: May | B6: 2023 | C6: =DATE(Occupancy_table[[#This Row],[Year]], MATCH(Occupancy_table[[#This Row],[Month]],{"Jan","Feb","Mar","Apr","May","Jun","Jul","Aug","Sep","Oct","Nov","Dec"},0),1) -> 45047 | D6: =SUMIFS(Daily_Data[[#All],[Rooms_Occupied]],Daily_Data[[#All],[Month_key]],Occupancy_table[[#All],[Month_Key]]) -> 364
A7: Jun | B7: 2023 | C7: =DATE(Occupancy_table[[#This Row],[Year]], MATCH(Occupancy_table[[#This Row],[Month]],{"Jan","Feb","Mar","Apr","May","Jun","Jul","Aug","Sep","Oct","Nov","Dec"},0),1) -> 45078 | D7: =SUMIFS(Daily_Data[[#All],[Rooms_Occupied]],Daily_Data[[#All],[Month_key]],Occupancy_table[[#All],[Month_Key]]) -> 328
A8: Jul | B8: 2023 | C8: =DATE(Occupancy_table[[#This Row],[Year]], MATCH(Occupancy_table[[#This Row],[Month]],{"Jan","Feb","Mar","Apr","May","Jun","Jul","Aug","Sep","Oct","Nov","Dec"},0),1) -> 45108 | D8: =SUMIFS(Daily_Data[[#All],[Rooms_Occupied]],Daily_Data[[#All],[Month_key]],Occupancy_table[[#All],[Month_Key]]) -> 333
A9: Aug | B9: 2023 | C9: =DATE(Occupancy_table[[#This Row],[Year]], MATCH(Occupancy_table[[#This Row],[Month]],{"Jan","Feb","Mar","Apr","May","Jun","Jul","Aug","Sep","Oct","Nov","Dec"},0),1) -> 45139 | D9: =SUMIFS(Daily_Data[[#All],[Rooms_Occupied]],Daily_Data[[#All],[Month_key]],Occupancy_table[[#All],[Month_Key]]) -> 338
A10: Sep | B10: 2023 | C10: =DATE(Occupancy_table[[#This Row],[Year]], MATCH(Occupancy_table[[#This Row],[Month]],{"Jan","Feb","Mar","Apr","May","Jun","Jul","Aug","Sep","Oct","Nov","Dec"},0),1) -> 45170 | D10: =SUMIFS(Daily_Data[[#All],[Rooms_Occupied]],Daily_Data[[#All],[Month_key]],Occupancy_table[[#All],[Month_Key]]) -> 330
A11: Oct | B11: 2023 | C11: =DATE(Occupancy_table[[#This Row],[Year]], MATCH(Occupancy_table[[#This Row],[Month]],{"Jan","Feb","Mar","Apr","May","Jun","Jul","Aug","Sep","Oct","Nov","Dec"},0),1) -> 45200 | D11: =SUMIFS(Daily_Data[[#All],[Rooms_Occupied]],Daily_Data[[#All],[Month_key]],Occupancy_table[[#All],[Month_Key]]) -> 336
A12: Nov | B12: 2023 | C12: =DATE(Occupancy_table[[#This Row],[Year]], MATCH(Occupancy_table[[#This Row],[Month]],{"Jan","Feb","Mar","Apr","May","Jun","Jul","Aug","Sep","Oct","Nov","Dec"},0),1) -> 45231 | D12: =SUMIFS(Daily_Data[[#All],[Rooms_Occupied]],Daily_Data[[#All],[Month_key]],Occupancy_table[[#All],[Month_Key]]) -> 340
A13: Dec | B13: 2023 | C13: =DATE(Occupancy_table[[#This Row],[Year]], MATCH(Occupancy_table[[#This Row],[Month]],{"Jan","Feb","Mar","Apr","May","Jun","Jul","Aug","Sep","Oct","Nov","Dec"},0),1) -> 45261 | D13: =SUMIFS(Daily_Data[[#All],[Rooms_Occupied]],Daily_Data[[#All],[Month_key]],Occupancy_table[[#All],[Month_Key]]) -> 333
... A25: Dec | B25: 2024 | C25: =DATE(Occupancy_table[[#This Row],[Year]], MATCH(Occupancy_table[[#This Row],[Month]],{"Jan","Feb","Mar","Apr","May","Jun","Jul","Aug","Sep","Oct","Nov","Dec"},0),1) -> 45627 | D25: =SUMIFS(Daily_Data[[#All],[Rooms_Occupied]],Daily_Data[[#All],[Month_key]],Occupancy_table[[#All],[Month_Key]]) -> 332

Sheet Monthly_Summary
A1: Month_Key | B1: Month | C1: Year | D1: Days_in_Month | E1: Total_Sales | F1: Total_Expense | G1: Total_Profit | H1: Total_rooms_sold | I1: Max_Rooms | J1: ADR (Average Daily Rate) | K1: occupancy % | L1: Monthly_RevPar
A2: 44927 | B2: =TEXT(Monthly_Summary[[#This Row],[Month_Key]], "MMMM") -> January | C2: =TEXT(Monthly_Summary[[#This Row],[Month_Key]],"YYYY") -> 2023 | D2: =DAY(EOMONTH(Monthly_Summary[[#This Row],[Month_Key]],0)) -> 31 | E2: =SUMIFS(Daily_Data[Total_Sales],Daily_Data[Month_key],Monthly_Summary!A2) -> 574450 | F2: =SUMIFS(Expense_master[Total_expense],Expense_master[Month_Key],Monthly_Summary[[#This Row],[Month_Key]]) -> 469091 | G2: =SUMIFS(Daily_Data[Profit],Daily_Data[Month_key],Monthly_Summary[[#This Row],[Month_Key]]) -> 105359 | H2: =SUMIFS(Occupancy_table[Monthly_rooms_Occupied],Occupancy_table[Month_Key],Monthly_Summary[[#This Row],[Month_Key]]) -> 358 | I2: =MAX(Daily_Data[Max_rooms]) -> 14 | J2: =Monthly_Summary[[#This Row],[Total_Sales]]/Monthly_Summary[[#This Row],[Total_rooms_sold]] -> 1604.6089 | K2: =(Monthly_Summary[[#This Row],[Total_rooms_sold]] / (Monthly_Summary[[#This Row],[Max_Rooms]] *Monthly_Summary[[#This Row],[Days_in_Month]])) -> 0.82488479 | L2: =Monthly_Summary[[#This Row],[Total_Sales]] / (Monthly_Summary[[#This Row],[Max_Rooms]] *Monthly_Summary[[#This Row],[Days_in_Month]]) -> 1323.6175
A3: 44958 | B3: =TEXT(Monthly_Summary[[#This Row],[Month_Key]], "MMMM") -> February | C3: =TEXT(Monthly_Summary[[#This Row],[Month_Key]],"YYYY") -> 2023 | D3: =DAY(EOMONTH(Monthly_Summary[[#This Row],[Month_Key]],0)) -> 28 | E3: =SUMIFS(Daily_Data[Total_Sales],Daily_Data[Month_key],Monthly_Summary!A3) -> 473574 | F3: =SUMIFS(Expense_master[Total_expense],Expense_master[Month_Key],Monthly_Summary[[#This Row],[Month_Key]]) -> 444469.28 | G3: =SUMIFS(Daily_Data[Profit],Daily_Data[Month_key],Monthly_Summary[[#This Row],[Month_Key]]) -> 29104.72 | H3: =SUMIFS(Occupancy_table[Monthly_rooms_Occupied],Occupancy_table[Month_Key],Monthly_Summary[[#This Row],[Month_Key]]) -> 316 | I3: =MAX(Daily_Data[Max_rooms]) -> 14 | J3: =Monthly_Summary[[#This Row],[Total_Sales]]/Monthly_Summary[[#This Row],[Total_rooms_sold]] -> 1498.6519 | K3: =(Monthly_Summary[[#This Row],[Total_rooms_sold]] / (Monthly_Summary[[#This Row],[Max_Rooms]] *Monthly_Summary[[#This Row],[Days_in_Month]])) -> 0.80612245 | L3: =Monthly_Summary[[#This Row],[Total_Sales]] / (Monthly_Summary[[#This Row],[Max_Rooms]] *Monthly_Summary[[#This Row],[Days_in_Month]]) -> 1208.0969 | O3: Total Revenue | P3: =SUM(Monthly_Summary[Total_Sales]) -> 12036097
A4: 44986 | B4: =TEXT(Monthly_Summary[[#This Row],[Month_Key]], "MMMM") -> March | C4: =TEXT(Monthly_Summary[[#This Row],[Month_Key]],"YYYY") -> 2023 | D4: =DAY(EOMONTH(Monthly_Summary[[#This Row],[Month_Key]],0)) -> 31 | E4: =SUMIFS(Daily_Data[Total_Sales],Daily_Data[Month_key],Monthly_Summary!A4) -> 506127 | F4: =SUMIFS(Expense_master[Total_expense],Expense_master[Month_Key],Monthly_Summary[[#This Row],[Month_Key]]) -> 449937.94 | G4: =SUMIFS(Daily_Data[Profit],Daily_Data[Month_key],Monthly_Summary[[#This Row],[Month_Key]]) -> 56189.06 | H4: =SUMIFS(Occupancy_table[Monthly_rooms_Occupied],Occupancy_table[Month_Key],Monthly_Summary[[#This Row],[Month_Key]]) -> 342 | I4: =MAX(Daily_Data[Max_rooms]) -> 14 | J4: =Monthly_Summary[[#This Row],[Total_Sales]]/Monthly_Summary[[#This Row],[Total_rooms_sold]] -> 1479.9035 | K4: =(Monthly_Summary[[#This Row],[Total_rooms_sold]] / (Monthly_Summary[[#This Row],[Max_Rooms]] *Monthly_Summary[[#This Row],[Days_in_Month]])) -> 0.78801843 | L4: =Monthly_Summary[[#This Row],[Total_Sales]] / (Monthly_Summary[[#This Row],[Max_Rooms]] *Monthly_Summary[[#This Row],[Days_in_Month]]) -> 1166.1912 | O4: Avg ADR | P4: =AVERAGE(Monthly_Summary[ADR (Average Daily Rate)]) -> 1508.9904
A5: 45017 | B5: =TEXT(Monthly_Summary[[#This Row],[Month_Key]], "MMMM") -> April | C5: =TEXT(Monthly_Summary[[#This Row],[Month_Key]],"YYYY") -> 2023 | D5: =DAY(EOMONTH(Monthly_Summary[[#This Row],[Month_Key]],0)) -> 30 | E5: =SUMIFS(Daily_Data[Total_Sales],Daily_Data[Month_key],Monthly_Summary!A5) -> 490116 | F5: =SUMIFS(Expense_master[Total_expense],Expense_master[Month_Key],Monthly_Summary[[#This Row],[Month_Key]]) -> 466755.52 | G5: =SUMIFS(Daily_Data[Profit],Daily_Data[Month_key],Monthly_Summary[[#This Row],[Month_Key]]) -> 23360.48 | H5: =SUMIFS(Occupancy_table[Monthly_rooms_Occupied],Occupancy_table[Month_Key],Monthly_Summary[[#This Row],[Month_Key]]) -> 321 | I5: =MAX(Daily_Data[Max_rooms]) -> 14 | J5: =Monthly_Summary[[#This Row],[Total_Sales]]/Monthly_Summary[[#This Row],[Total_rooms_sold]] -> 1526.8411 | K5: =(Monthly_Summary[[#This Row],[Total_rooms_sold]] / (Monthly_Summary[[#This Row],[Max_Rooms]] *Monthly_Summary[[#This Row],[Days_in_Month]])) -> 0.76428571 | L5: =Monthly_Summary[[#This Row],[Total_Sales]] / (Monthly_Summary[[#This Row],[Max_Rooms]] *Monthly_Summary[[#This Row],[Days_in_Month]]) -> 1166.9429 | O5: Net Profit | P5: =SUM(Monthly_Summary[Total_Profit]) -> 420821.66
A6: 45047 | B6: =TEXT(Monthly_Summary[[#This Row],[Month_Key]], "MMMM") -> May | C6: =TEXT(Monthly_Summary[[#This Row],[Month_Key]],"YYYY") -> 2023 | D6: =DAY(EOMONTH(Monthly_Summary[[#This Row],[Month_Key]],0)) -> 31 | E6: =SUMIFS(Daily_Data[Total_Sales],Daily_Data[Month_key],Monthly_Summary!A6) -> 545459 | F6: =SUMIFS(Expense_master[Total_expense],Expense_master[Month_Key],Monthly_Summary[[#This Row],[Month_Key]]) -> 481290.98 | G6: =SUMIFS(Daily_Data[Profit],Daily_Data[Month_key],Monthly_Summary[[#This Row],[Month_Key]]) -> 64168.02 | H6: =SUMIFS(Occupancy_table[Monthly_rooms_Occupied],Occupancy_table[Month_Key],Monthly_Summary[[#This Row],[Month_Key]]) -> 364 | I6: =MAX(Daily_Data[Max_rooms]) -> 14 | J6: =Monthly_Summary[[#This Row],[Total_Sales]]/Monthly_Summary[[#This Row],[Total_rooms_sold]] -> 1498.5137 | K6: =(Monthly_Summary[[#This Row],[Total_rooms_sold]] / (Monthly_Summary[[#This Row],[Max_Rooms]] *Monthly_Summary[[#This Row],[Days_in_Month]])) -> 0.83870968 | L6: =Monthly_Summary[[#This Row],[Total_Sales]] / (Monthly_Summary[[#This Row],[Max_Rooms]] *Monthly_Summary[[#This Row],[Days_in_Month]]) -> 1256.818 | O6: Total Rooms Sold | P6: =SUM(Monthly_Summary[Total_rooms_sold]) -> 7974
A7: 45078 | B7: =TEXT(Monthly_Summary[[#This Row],[Month_Key]], "MMMM") -> June | C7: =TEXT(Monthly_Summary[[#This Row],[Month_Key]],"YYYY") -> 2023 | D7: =DAY(EOMONTH(Monthly_Summary[[#This Row],[Month_Key]],0)) -> 30 | E7: =SUMIFS(Daily_Data[Total_Sales],Daily_Data[Month_key],Monthly_Summary!A7) -> 494272 | F7: =SUMIFS(Expense_master[Total_expense],Expense_master[Month_Key],Monthly_Summary[[#This Row],[Month_Key]]) -> 467157.84 | G7: =SUMIFS(Daily_Data[Profit],Daily_Data[Month_key],Monthly_Summary[[#This Row],[Month_Key]]) -> 27114.16 | H7: =SUMIFS(Occupancy_table[Monthly_rooms_Occupied],Occupancy_table[Month_Key],Monthly_Summary[[#This Row],[Month_Key]]) -> 328 | I7: =MAX(Daily_Data[Max_rooms]) -> 14 | J7: =Monthly_Summary[[#This Row],[Total_Sales]]/Monthly_Summary[[#This Row],[Total_rooms_sold]] -> 1506.9268 | K7: =(Monthly_Summary[[#This Row],[Total_rooms_sold]] / (Monthly_Summary[[#This Row],[Max_Rooms]] *Monthly_Summary[[#This Row],[Days_in_Month]])) -> 0.78095238 | L7: =Monthly_Summary[[#This Row],[Total_Sales]] / (Monthly_Summary[[#This Row],[Max_Rooms]] *Monthly_Summary[[#This Row],[Days_in_Month]]) -> 1176.8381 | O7: Average Occupancy | P7: =AVERAGE(Monthly_Summary[occupancy %]) -> 0.77928659
A8: 45108 | B8: =TEXT(Monthly_Summary[[#This Row],[Month_Key]], "MMMM") -> July | C8: =TEXT(Monthly_Summary[[#This Row],[Month_Key]],"YYYY") -> 2023 | D8: =DAY(EOMONTH(Monthly_Summary[[#This Row],[Month_Key]],0)) -> 31 | E8: =SUMIFS(Daily_Data[Total_Sales],Daily_Data[Month_key],Monthly_Summary!A8) -> 529245 | F8: =SUMIFS(Expense_master[Total_expense],Expense_master[Month_Key],Monthly_Summary[[#This Row],[Month_Key]]) -> 478000.9 | G8: =SUMIFS(Daily_Data[Profit],Daily_Data[Month_key],Monthly_Summary[[#This Row],[Month_Key]]) -> 51244.1 | H8: =SUMIFS(Occupancy_table[Monthly_rooms_Occupied],Occupancy_table[Month_Key],Monthly_Summary[[#This Row],[Month_Key]]) -> 333 | I8: =MAX(Daily_Data[Max_rooms]) -> 14 | J8: =Monthly_Summary[[#This Row],[Total_Sales]]/Monthly_Summary[[#This Row],[Total_rooms_sold]] -> 1589.3243 | K8: =(Monthly_Summary[[#This Row],[Total_rooms_sold]] / (Monthly_Summary[[#This Row],[Max_Rooms]] *Monthly_Summary[[#This Row],[Days_in_Month]])) -> 0.76728111 | L8: =Monthly_Summary[[#This Row],[Total_Sales]] / (Monthly_Summary[[#This Row],[Max_Rooms]] *Monthly_Summary[[#This Row],[Days_in_Month]]) -> 1219.4585 | O8: Average RevPar | P8: =AVERAGE(Monthly_Summary[Monthly_RevPar]) -> 1176.0663
A9: 45139 | B9: =TEXT(Monthly_Summary[[#This Row],[Month_Key]], "MMMM") -> August | C9: =TEXT(Monthly_Summary[[#This Row],[Month_Key]],"YYYY") -> 2023 | D9: =DAY(EOMONTH(Monthly_Summary[[#This Row],[Month_Key]],0)) -> 31 | E9: =SUMIFS(Daily_Data[Total_Sales],Daily_Data[Month_key],Monthly_Summary!A9) -> 490221 | F9: =SUMIFS(Expense_master[Total_expense],Expense_master[Month_Key],Monthly_Summary[[#This Row],[Month_Key]]) -> 468727.62 | G9: =SUMIFS(Daily_Data[Profit],Daily_Data[Month_key],Monthly_Summary[[#This Row],[Month_Key]]) -> 21493.38 | H9: =SUMIFS(Occupancy_table[Monthly_rooms_Occupied],Occupancy_table[Month_Key],Monthly_Summary[[#This Row],[Month_Key]]) -> 338 | I9: =MAX(Daily_Data[Max_rooms]) -> 14 | J9: =Monthly_Summary[[#This Row],[Total_Sales]]/Monthly_Summary[[#This Row],[Total_rooms_sold]] -> 1450.358 | K9: =(Monthly_Summary[[#This Row],[Total_rooms_sold]] / (Monthly_Summary[[#This Row],[Max_Rooms]] *Monthly_Summary[[#This Row],[Days_in_Month]])) -> 0.77880184 | L9: =Monthly_Summary[[#This Row],[Total_Sales]] / (Monthly_Summary[[#This Row],[Max_Rooms]] *Monthly_Summary[[#This Row],[Days_in_Month]]) -> 1129.5415 | O9: Total Expense | P9: =SUM(Monthly_Summary[Total_Expense]) -> 11615275
A10: 45170 | B10: =TEXT(Monthly_Summary[[#This Row],[Month_Key]], "MMMM") -> September | C10: =TEXT(Monthly_Summary[[#This Row],[Month_Key]],"YYYY") -> 2023 | D10: =DAY(EOMONTH(Monthly_Summary[[#This Row],[Month_Key]],0)) -> 30 | E10: =SUMIFS(Daily_Data[Total_Sales],Daily_Data[Month_key],Monthly_Summary!A10) -> 496169 | F10: =SUMIFS(Expense_master[Total_expense],Expense_master[Month_Key],Monthly_Summary[[#This Row],[Month_Key]]) -> 472490.18 | G10: =SUMIFS(Daily_Data[Profit],Daily_Data[Month_key],Monthly_Summary[[#This Row],[Month_Key]]) -> 23678.82 | H10: =SUMIFS(Occupancy_table[Monthly_rooms_Occupied],Occupancy_table[Month_Key],Monthly_Summary[[#This Row],[Month_Key]]) -> 330 | I10: =MAX(Daily_Data[Max_rooms]) -> 14 | J10: =Monthly_Summary[[#This Row],[Total_Sales]]/Monthly_Summary[[#This Row],[Total_rooms_sold]] -> 1503.5424 | K10: =(Monthly_Summary[[#This Row],[Total_rooms_sold]] / (Monthly_Summary[[#This Row],[Max_Rooms]] *Monthly_Summary[[#This Row],[Days_in_Month]])) -> 0.78571429 | L10: =Monthly_Summary[[#This Row],[Total_Sales]] / (Monthly_Summary[[#This Row],[Max_Rooms]] *Monthly_Summary[[#This Row],[Days_in_Month]]) -> 1181.3548 | O10: OTA Commission | P10: =SUM(Daily_Data[OTA Commision]) / SUM(Daily_Data[Total_Sales]) -> 0.22
A11: 45200 | B11: =TEXT(Monthly_Summary[[#This Row],[Month_Key]], "MMMM") -> October | C11: =TEXT(Monthly_Summary[[#This Row],[Month_Key]],"YYYY") -> 2023 | D11: =DAY(EOMONTH(Monthly_Summary[[#This Row],[Month_Key]],0)) -> 31 | E11: =SUMIFS(Daily_Data[Total_Sales],Daily_Data[Month_key],Monthly_Summary!A11) -> 514925 | F11: =SUMIFS(Expense_master[Total_expense],Expense_master[Month_Key],Monthly_Summary[[#This Row],[Month_Key]]) -> 475132.5 | G11: =SUMIFS(Daily_Data[Profit],Daily_Data[Month_key],Monthly_Summary[[#This Row],[Month_Key]]) -> 39792.5 | H11: =SUMIFS(Occupancy_table[Monthly_rooms_Occupied],Occupancy_table[Month_Key],Monthly_Summary[[#This Row],[Month_Key]]) -> 336 | I11: =MAX(Daily_Data[Max_rooms]) -> 14 | J11: =Monthly_Summary[[#This Row],[Total_Sales]]/Monthly_Summary[[#This Row],[Total_rooms_sold]] -> 1532.5149 | K11: =(Monthly_Summary[[#This Row],[Total_rooms_sold]] / (Monthly_Summary[[#This Row],[Max_Rooms]] *Monthly_Summary[[#This Row],[Days_in_Month]])) -> 0.77419355 | L11: =Monthly_Summary[[#This Row],[Total_Sales]] / (Monthly_Summary[[#This Row],[Max_Rooms]] *Monthly_Summary[[#This Row],[Days_in_Month]]) -> 1186.4631 | O11: Highest Revenue Month | P11: =MAX(Monthly_Summary[Total_Sales]) -> 574450
A12: 45231 | B12: =TEXT(Monthly_Summary[[#This Row],[Month_Key]], "MMMM") -> November | C12: =TEXT(Monthly_Summary[[#This Row],[Month_Key]],"YYYY") -> 2023 | D12: =DAY(EOMONTH(Monthly_Summary[[#This Row],[Month_Key]],0)) -> 30 | E12: =SUMIFS(Daily_Data[Total_Sales],Daily_Data[Month_key],Monthly_Summary!A12) -> 500959 | F12: =SUMIFS(Expense_master[Total_expense],Expense_master[Month_Key],Monthly_Summary[[#This Row],[Month_Key]]) -> 472529.98 | G12: =SUMIFS(Daily_Data[Profit],Daily_Data[Month_key],Monthly_Summary[[#This Row],[Month_Key]]) -> 28429.02 | H12: =SUMIFS(Occupancy_table[Monthly_rooms_Occupied],Occupancy_table[Month_Key],Monthly_Summary[[#This Row],[Month_Key]]) -> 340 | I12: =MAX(Daily_Data[Max_rooms]) -> 14 | J12: =Monthly_Summary[[#This Row],[Total_Sales]]/Monthly_Summary[[#This Row],[Total_rooms_sold]] -> 1473.4088 | K12: =(Monthly_Summary[[#This Row],[Total_rooms_sold]] / (Monthly_Summary[[#This Row],[Max_Rooms]] *Monthly_Summary[[#This Row],[Days_in_Month]])) -> 0.80952381 | L12: =Monthly_Summary[[#This Row],[Total_Sales]] / (Monthly_Summary[[#This Row],[Max_Rooms]] *Monthly_Summary[[#This Row],[Days_in_Month]]) -> 1192.7595 | O12: Lowest Revenue Month | P12: =MIN(Monthly_Summary[Total_Sales]) -> 428169
A13: 45261 | B13: =TEXT(Monthly_Summary[[#This Row],[Month_Key]], "MMMM") -> December | C13: =TEXT(Monthly_Summary[[#This Row],[Month_Key]],"YYYY") -> 2023 | D13: =DAY(EOMONTH(Monthly_Summary[[#This Row],[Month_Key]],0)) -> 31 | E13: =SUMIFS(Daily_Data[Total_Sales],Daily_Data[Month_key],Monthly_Summary!A13) -> 497279 | F13: =SUMIFS(Expense_master[Total_expense],Expense_master[Month_Key],Monthly_Summary[[#This Row],[Month_Key]]) -> 469340.38 | G13: =SUMIFS(Daily_Data[Profit],Daily_Data[Month_key],Monthly_Summary[[#This Row],[Month_Key]]) -> 27938.62 | H13: =SUMIFS(Occupancy_table[Monthly_rooms_Occupied],Occupancy_table[Month_Key],Monthly_Summary[[#This Row],[Month_Key]]) -> 333 | I13: =MAX(Daily_Data[Max_rooms]) -> 14 | J13: =Monthly_Summary[[#This Row],[Total_Sales]]/Monthly_Summary[[#This Row],[Total_rooms_sold]] -> 1493.3303 | K13: =(Monthly_Summary[[#This Row],[Total_rooms_sold]] / (Monthly_Summary[[#This Row],[Max_Rooms]] *Monthly_Summary[[#This Row],[Days_in_Month]])) -> 0.76728111 | L13: =Monthly_Summary[[#This Row],[Total_Sales]] / (Monthly_Summary[[#This Row],[Max_Rooms]] *Monthly_Summary[[#This Row],[Days_in_Month]]) -> 1145.8041 | O13: highest RevPar grwoth % | P13: =(L25-L2) / L2 -> -0.14868831
A14: 45292 | B14: =TEXT(Monthly_Summary[[#This Row],[Month_Key]], "MMMM") -> January | C14: =TEXT(Monthly_Summary[[#This Row],[Month_Key]],"YYYY") -> 2024 | D14: =DAY(EOMONTH(Monthly_Summary[[#This Row],[Month_Key]],0)) -> 31 | E14: =SUMIFS(Daily_Data[Total_Sales],Daily_Data[Month_key],Monthly_Summary!A14) -> 498371 | F14: =SUMIFS(Expense_master[Total_expense],Expense_master[Month_Key],Monthly_Summary[[#This Row],[Month_Key]]) -> 473921.62 | G14: =SUMIFS(Daily_Data[Profit],Daily_Data[Month_key],Monthly_Summary[[#This Row],[Month_Key]]) -> 24449.38 | H14: =SUMIFS(Occupancy_table[Monthly_rooms_Occupied],Occupancy_table[Month_Key],Monthly_Summary[[#This Row],[Month_Key]]) -> 319 | I14: =MAX(Daily_Data[Max_rooms]) -> 14 | J14: =Monthly_Summary[[#This Row],[Total_Sales]]/Monthly_Summary[[#This Row],[Total_rooms_sold]] -> 1562.2915 | K14: =(Monthly_Summary[[#This Row],[Total_rooms_sold]] / (Monthly_Summary[[#This Row],[Max_Rooms]] *Monthly_Summary[[#This Row],[Days_in_Month]])) -> 0.73502304 | L14: =Monthly_Summary[[#This Row],[Total_Sales]] / (Monthly_Summary[[#This Row],[Max_Rooms]] *Monthly_Summary[[#This Row],[Days_in_Month]]) -> 1148.3203
A15: 45323 | B15: =TEXT(Monthly_Summary[[#This Row],[Month_Key]], "MMMM") -> February | C15: =TEXT(Monthly_Summary[[#This Row],[Month_Key]],"YYYY") -> 2024 | D15: =DAY(EOMONTH(Monthly_Summary[[#This Row],[Month_Key]],0)) -> 29 | E15: =SUMIFS(Daily_Data[Total_Sales],Daily_Data[Month_key],Monthly_Summary!A15) -> 428169 | F15: =SUMIFS(Expense_master[Total_expense],Expense_master[Month_Key],Monthly_Summary[[#This Row],[Month_Key]]) -> 454413.18 | G15: =SUMIFS(Daily_Data[Profit],Daily_Data[Month_key],Monthly_Summary[[#This Row],[Month_Key]]) -> -26244.18 | H15: =SUMIFS(Occupancy_table[Monthly_rooms_Occupied],Occupancy_table[Month_Key],Monthly_Summary[[#This Row],[Month_Key]]) -> 301 | I15: =MAX(Daily_Data[Max_rooms]) -> 14 | J15: =Monthly_Summary[[#This Row],[Total_Sales]]/Monthly_Summary[[#This Row],[Total_rooms_sold]] -> 1422.4884 | K15: =(Monthly_Summary[[#This Row],[Total_rooms_sold]] / (Monthly_Summary[[#This Row],[Max_Rooms]] *Monthly_Summary[[#This Row],[Days_in_Month]])) -> 0.74137931 | L15: =Monthly_Summary[[#This Row],[Total_Sales]] / (Monthly_Summary[[#This Row],[Max_Rooms]] *Monthly_Summary[[#This Row],[Days_in_Month]]) -> 1054.6034
A16: 45352 | B16: =TEXT(Monthly_Summary[[#This Row],[Month_Key]], "MMMM") -> March | C16: =TEXT(Monthly_Summary[[#This Row],[Month_Key]],"YYYY") -> 2024 | D16: =DAY(EOMONTH(Monthly_Summary[[#This Row],[Month_Key]],0)) -> 31 | E16: =SUMIFS(Daily_Data[Total_Sales],Daily_Data[Month_key],Monthly_Summary!A16) -> 495274 | F16: =SUMIFS(Expense_master[Total_expense],Expense_master[Month_Key],Monthly_Summary[[#This Row],[Month_Key]]) -> 472202.28 | G16: =SUMIFS(Daily_Data[Profit],Daily_Data[Month_key],Monthly_Summary[[#This Row],[Month_Key]]) -> 23071.72 | H16: =SUMIFS(Occupancy_table[Monthly_rooms_Occupied],Occupancy_table[Month_Key],Monthly_Summary[[#This Row],[Month_Key]]) -> 335 | I16: =MAX(Daily_Data[Max_rooms]) -> 14 | J16: =Monthly_Summary[[#This Row],[Total_Sales]]/Monthly_Summary[[#This Row],[Total_rooms_sold]] -> 1478.4299 | K16: =(Monthly_Summary[[#This Row],[Total_rooms_sold]] / (Monthly_Summary[[#This Row],[Max_Rooms]] *Monthly_Summary[[#This Row],[Days_in_Month]])) -> 0.7718894 | L16: =Monthly_Summary[[#This Row],[Total_Sales]] / (Monthly_Summary[[#This Row],[Max_Rooms]] *Monthly_Summary[[#This Row],[Days_in_Month]]) -> 1141.1843
A17: 45383 | B17: =TEXT(Monthly_Summary[[#This Row],[Month_Key]], "MMMM") -> April | C17: =TEXT(Monthly_Summary[[#This Row],[Month_Key]],"YYYY") -> 2024 | D17: =DAY(EOMONTH(Monthly_Summary[[#This Row],[Month_Key]],0)) -> 30 | E17: =SUMIFS(Daily_Data[Total_Sales],Daily_Data[Month_key],Monthly_Summary!A17) -> 501755 | F17: =SUMIFS(Expense_master[Total_expense],Expense_master[Month_Key],Monthly_Summary[[#This Row],[Month_Key]]) -> 512666.1 | G17: =SUMIFS(Daily_Data[Profit],Daily_Data[Month_key],Monthly_Summary[[#This Row],[Month_Key]]) -> -10911.1 | H17: =SUMIFS(Occupancy_table[Monthly_rooms_Occupied],Occupancy_table[Month_Key],Monthly_Summary[[#This Row],[Month_Key]]) -> 331 | I17: =MAX(Daily_Data[Max_rooms]) -> 14 | J17: =Monthly_Summary[[#This Row],[Total_Sales]]/Monthly_Summary[[#This Row],[Total_rooms_sold]] -> 1515.8761 | K17: =(Monthly_Summary[[#This Row],[Total_rooms_sold]] / (Monthly_Summary[[#This Row],[Max_Rooms]] *Monthly_Summary[[#This Row],[Days_in_Month]])) -> 0.78809524 | L17: =Monthly_Summary[[#This Row],[Total_Sales]] / (Monthly_Summary[[#This Row],[Max_Rooms]] *Monthly_Summary[[#This Row],[Days_in_Month]]) -> 1194.6548
A18: 45413 | B18: =TEXT(Monthly_Summary[[#This Row],[Month_Key]], "MMMM") -> May | C18: =TEXT(Monthly_Summary[[#This Row],[Month_Key]],"YYYY") -> 2024 | D18: =DAY(EOMONTH(Monthly_Summary[[#This Row],[Month_Key]],0)) -> 31 | E18: =SUMIFS(Daily_Data[Total_Sales],Daily_Data[Month_key],Monthly_Summary!A18) -> 483000 | F18: =SUMIFS(Expense_master[Total_expense],Expense_master[Month_Key],Monthly_Summary[[#This Row],[Month_Key]]) -> 511260 | G18: =SUMIFS(Daily_Data[Profit],Daily_Data[Month_key],Monthly_Summary[[#This Row],[Month_Key]]) -> -28260 | H18: =SUMIFS(Occupancy_table[Monthly_rooms_Occupied],Occupancy_table[Month_Key],Monthly_Summary[[#This Row],[Month_Key]]) -> 326 | I18: =MAX(Daily_Data[Max_rooms]) -> 14 | J18: =Monthly_Summary[[#This Row],[Total_Sales]]/Monthly_Summary[[#This Row],[Total_rooms_sold]] -> 1481.5951 | K18: =(Monthly_Summary[[#This Row],[Total_rooms_sold]] / (Monthly_Summary[[#This Row],[Max_Rooms]] *Monthly_Summary[[#This Row],[Days_in_Month]])) -> 0.75115207 | L18: =Monthly_Summary[[#This Row],[Total_Sales]] / (Monthly_Summary[[#This Row],[Max_Rooms]] *Monthly_Summary[[#This Row],[Days_in_Month]]) -> 1112.9032
A19: 45444 | B19: =TEXT(Monthly_Summary[[#This Row],[Month_Key]], "MMMM") -> June | C19: =TEXT(Monthly_Summary[[#This Row],[Month_Key]],"YYYY") -> 2024 | D19: =DAY(EOMONTH(Monthly_Summary[[#This Row],[Month_Key]],0)) -> 30 | E19: =SUMIFS(Daily_Data[Total_Sales],Daily_Data[Month_key],Monthly_Summary!A19) -> 522323 | F19: =SUMIFS(Expense_master[Total_expense],Expense_master[Month_Key],Monthly_Summary[[#This Row],[Month_Key]]) -> 513406.06 | G19: =SUMIFS(Daily_Data[Profit],Daily_Data[Month_key],Monthly_Summary[[#This Row],[Month_Key]]) -> 8916.94 | H19: =SUMIFS(Occupancy_table[Monthly_rooms_Occupied],Occupancy_table[Month_Key],Monthly_Summary[[#This Row],[Month_Key]]) -> 334 | I19: =MAX(Daily_Data[Max_rooms]) -> 14 | J19: =Monthly_Summary[[#This Row],[Total_Sales]]/Monthly_Summary[[#This Row],[Total_rooms_sold]] -> 1563.8413 | K19: =(Monthly_Summary[[#This Row],[Total_rooms_sold]] / (Monthly_Summary[[#This Row],[Max_Rooms]] *Monthly_Summary[[#This Row],[Days_in_Month]])) -> 0.7952381 | L19: =Monthly_Summary[[#This Row],[Total_Sales]] / (Monthly_Summary[[#This Row],[Max_Rooms]] *Monthly_Summary[[#This Row],[Days_in_Month]]) -> 1243.6262
A20: 45474 | B20: =TEXT(Monthly_Summary[[#This Row],[Month_Key]], "MMMM") -> July | C20: =TEXT(Monthly_Summary[[#This Row],[Month_Key]],"YYYY") -> 2024 | D20: =DAY(EOMONTH(Monthly_Summary[[#This Row],[Month_Key]],0)) -> 31 | E20: =SUMIFS(Daily_Data[Total_Sales],Daily_Data[Month_key],Monthly_Summary!A20) -> 488306 | F20: =SUMIFS(Expense_master[Total_expense],Expense_master[Month_Key],Monthly_Summary[[#This Row],[Month_Key]]) -> 509205.32 | G20: =SUMIFS(Daily_Data[Profit],Daily_Data[Month_key],Monthly_Summary[[#This Row],[Month_Key]]) -> -20899.32 | H20: =SUMIFS(Occupancy_table[Monthly_rooms_Occupied],Occupancy_table[Month_Key],Monthly_Summary[[#This Row],[Month_Key]]) -> 331 | I20: =MAX(Daily_Data[Max_rooms]) -> 14 | J20: =Monthly_Summary[[#This Row],[Total_Sales]]/Monthly_Summary[[#This Row],[Total_rooms_sold]] -> 1475.2447 | K20: =(Monthly_Summary[[#This Row],[Total_rooms_sold]] / (Monthly_Summary[[#This Row],[Max_Rooms]] *Monthly_Summary[[#This Row],[Days_in_Month]])) -> 0.76267281 | L20: =Monthly_Summary[[#This Row],[Total_Sales]] / (Monthly_Summary[[#This Row],[Max_Rooms]] *Monthly_Summary[[#This Row],[Days_in_Month]]) -> 1125.129
A21: 45505 | B21: =TEXT(Monthly_Summary[[#This Row],[Month_Key]], "MMMM") -> August | C21: =TEXT(Monthly_Summary[[#This Row],[Month_Key]],"YYYY") -> 2024 | D21: =DAY(EOMONTH(Monthly_Summary[[#This Row],[Month_Key]],0)) -> 31 | E21: =SUMIFS(Daily_Data[Total_Sales],Daily_Data[Month_key],Monthly_Summary!A21) -> 520814 | F21: =SUMIFS(Expense_master[Total_expense],Expense_master[Month_Key],Monthly_Summary[[#This Row],[Month_Key]]) -> 515690.08 | G21: =SUMIFS(Daily_Data[Profit],Daily_Data[Month_key],Monthly_Summary[[#This Row],[Month_Key]]) -> 5123.92 | H21: =SUMIFS(Occupancy_table[Monthly_rooms_Occupied],Occupancy_table[Month_Key],Monthly_Summary[[#This Row],[Month_Key]]) -> 332 | I21: =MAX(Daily_Data[Max_rooms]) -> 14 | J21: =Monthly_Summary[[#This Row],[Total_Sales]]/Monthly_Summary[[#This Row],[Total_rooms_sold]] -> 1568.7169 | K21: =(Monthly_Summary[[#This Row],[Total_rooms_sold]] / (Monthly_Summary[[#This Row],[Max_Rooms]] *Monthly_Summary[[#This Row],[Days_in_Month]])) -> 0.76497696 | L21: =Monthly_Summary[[#This Row],[Total_Sales]] / (Monthly_Summary[[#This Row],[Max_Rooms]] *Monthly_Summary[[#This Row],[Days_in_Month]]) -> 1200.0323
A22: 45536 | B22: =TEXT(Monthly_Summary[[#This Row],[Month_Key]], "MMMM") -> September | C22: =TEXT(Monthly_Summary[[#This Row],[Month_Key]],"YYYY") -> 2024 | D22: =DAY(EOMONTH(Monthly_Summary[[#This Row],[Month_Key]],0)) -> 30 | E22: =SUMIFS(Daily_Data[Total_Sales],Daily_Data[Month_key],Monthly_Summary!A22) -> 495387 | F22: =SUMIFS(Expense_master[Total_expense],Expense_master[Month_Key],Monthly_Summary[[#This Row],[Month_Key]]) -> 509139.14 | G22: =SUMIFS(Daily_Data[Profit],Daily_Data[Month_key],Monthly_Summary[[#This Row],[Month_Key]]) -> -13752.14 | H22: =SUMIFS(Occupancy_table[Monthly_rooms_Occupied],Occupancy_table[Month_Key],Monthly_Summary[[#This Row],[Month_Key]]) -> 332 | I22: =MAX(Daily_Data[Max_rooms]) -> 14 | J22: =Monthly_Summary[[#This Row],[Total_Sales]]/Monthly_Summary[[#This Row],[Total_rooms_sold]] -> 1492.1295 | K22: =(Monthly_Summary[[#This Row],[Total_rooms_sold]] / (Monthly_Summary[[#This Row],[Max_Rooms]] *Monthly_Summary[[#This Row],[Days_in_Month]])) -> 0.79047619 | L22: =Monthly_Summary[[#This Row],[Total_Sales]] / (Monthly_Summary[[#This Row],[Max_Rooms]] *Monthly_Summary[[#This Row],[Days_in_Month]]) -> 1179.4929
A23: 45566 | B23: =TEXT(Monthly_Summary[[#This Row],[Month_Key]], "MMMM") -> October | C23: =TEXT(Monthly_Summary[[#This Row],[Month_Key]],"YYYY") -> 2024 | D23: =DAY(EOMONTH(Monthly_Summary[[#This Row],[Month_Key]],0)) -> 31 | E23: =SUMIFS(Daily_Data[Total_Sales],Daily_Data[Month_key],Monthly_Summary!A23) -> 495635 | F23: =SUMIFS(Expense_master[Total_expense],Expense_master[Month_Key],Monthly_Summary[[#This Row],[Month_Key]]) -> 508927.7 | G23: =SUMIFS(Daily_Data[Profit],Daily_Data[Month_key],Monthly_Summary[[#This Row],[Month_Key]]) -> -13292.7 | H23: =SUMIFS(Occupancy_table[Monthly_rooms_Occupied],Occupancy_table[Month_Key],Monthly_Summary[[#This Row],[Month_Key]]) -> 325 | I23: =MAX(Daily_Data[Max_rooms]) -> 14 | J23: =Monthly_Summary[[#This Row],[Total_Sales]]/Monthly_Summary[[#This Row],[Total_rooms_sold]] -> 1525.0308 | K23: =(Monthly_Summary[[#This Row],[Total_rooms_sold]] / (Monthly_Summary[[#This Row],[Max_Rooms]] *Monthly_Summary[[#This Row],[Days_in_Month]])) -> 0.74884793 | L23: =Monthly_Summary[[#This Row],[Total_Sales]] / (Monthly_Summary[[#This Row],[Max_Rooms]] *Monthly_Summary[[#This Row],[Days_in_Month]]) -> 1142.0161
A24: 45597 | B24: =TEXT(Monthly_Summary[[#This Row],[Month_Key]], "MMMM") -> November | C24: =TEXT(Monthly_Summary[[#This Row],[Month_Key]],"YYYY") -> 2024 | D24: =DAY(EOMONTH(Monthly_Summary[[#This Row],[Month_Key]],0)) -> 30 | E24: =SUMIFS(Daily_Data[Total_Sales],Daily_Data[Month_key],Monthly_Summary!A24) -> 505231 | F24: =SUMIFS(Expense_master[Total_expense],Expense_master[Month_Key],Monthly_Summary[[#This Row],[Month_Key]]) -> 511244.82 | G24: =SUMIFS(Daily_Data[Profit],Daily_Data[Month_key],Monthly_Summary[[#This Row],[Month_Key]]) -> -6013.82 | H24: =SUMIFS(Occupancy_table[Monthly_rooms_Occupied],Occupancy_table[Month_Key],Monthly_Summary[[#This Row],[Month_Key]]) -> 337 | I24: =MAX(Daily_Data[Max_rooms]) -> 14 | J24: =Monthly_Summary[[#This Row],[Total_Sales]]/Monthly_Summary[[#This Row],[Total_rooms_sold]] -> 1499.2018 | K24: =(Monthly_Summary[[#This Row],[Total_rooms_sold]] / (Monthly_Summary[[#This Row],[Max_Rooms]] *Monthly_Summary[[#This Row],[Days_in_Month]])) -> 0.80238095 | L24: =Monthly_Summary[[#This Row],[Total_Sales]] / (Monthly_Summary[[#This Row],[Max_Rooms]] *Monthly_Summary[[#This Row],[Days_in_Month]]) -> 1202.931
A25: 45627 | B25: =TEXT(Monthly_Summary[[#This Row],[Month_Key]], "MMMM") -> December | C25: =TEXT(Monthly_Summary[[#This Row],[Month_Key]],"YYYY") -> 2024 | D25: =DAY(EOMONTH(Monthly_Summary[[#This Row],[Month_Key]],0)) -> 31 | E25: =SUMIFS(Daily_Data[Total_Sales],Daily_Data[Month_key],Monthly_Summary!A25) -> 489036 | F25: =SUMIFS(Expense_master[Total_expense],Expense_master[Month_Key],Monthly_Summary[[#This Row],[Month_Key]]) -> 508274.92 | G25: =SUMIFS(Daily_Data[Profit],Daily_Data[Month_key],Monthly_Summary[[#This Row],[Month_Key]]) -> -19238.92 | H25: =SUMIFS(Occupancy_table[Monthly_rooms_Occupied],Occupancy_table[Month_Key],Monthly_Summary[[#This Row],[Month_Key]]) -> 332 | I25: =MAX(Daily_Data[Max_rooms]) -> 14 | J25: =Monthly_Summary[[#This Row],[Total_Sales]]/Monthly_Summary[[#This Row],[Total_rooms_sold]] -> 1473 | K25: =(Monthly_Summary[[#This Row],[Total_rooms_sold]] / (Monthly_Summary[[#This Row],[Max_Rooms]] *Monthly_Summary[[#This Row],[Days_in_Month]])) -> 0.76497696 | L25: =Monthly_Summary[[#This Row],[Total_Sales]] / (Monthly_Summary[[#This Row],[Max_Rooms]] *Monthly_Summary[[#This Row],[Days_in_Month]]) -> 1126.8111

Sheet closing balacne
D4: Item | E4: Amount
D5: Total Operational Profit (modeled) | E5: =SUM(Daily_Data[Profit]) -> 420821.66
D6: Security Deposit Refund | E6: 320000
D7: Other Savings | E7: 160000
D8: Outstanding Liabilities | E8: 240000
D9: Closing Cash | E9: =E5+E6+E7-E8 -> 660821.66

Sheet Sheet1
